{ "tweet": {"text": "Ongoing hostage situation in Sydney café. #sydneyseige  Australian PM convenes National Security Committee of cabinet http://t.co/KDp8R6wdOm", "screenname": "BBCBreaking","date": "Mon Dec 15 02:27:59 CET 2014"},"languages" : { "columns": [[ "en", 83],[ "es", 3],[ "ru", 1],[ "fr", 1],[ "ja", 1] ], "groups": ["en","es","ru","fr","ja" ] },"themes" : { "columns": [[ "arts, culture and entertainment", 105],[ "social issue", 52],[ "economy, business and finance", 48],[ "sport", 44],[ "crime, law and justice", 43],[ "politics", 36],[ "human interest", 28],[ "unrest, conflicts and war", 26],[ "health", 20],[ "religion and belief", 17],[ "disaster and accident", 14],[ "science and technology", 10],[ "lifestyle and leisure", 8],[ "education", 5],[ "labour", 4],[ "arte, cultura y espectáculos", 3],[ "religión y credos", 3],[ "policía y justicia", 2],[ "deporte", 2],[ "weather", 2],[ "ciencia y tecnología", 1],[ "asuntos sociales", 1],[ "política", 1],[ "mano de obra", 1],[ "interés humano", 1] ], "groups": ["arts, culture and entertainment","social issue","economy, business and finance","sport","crime, law and justice","politics","human interest","unrest, conflicts and war","health","religion and belief","disaster and accident","science and technology","lifestyle and leisure","education","labour","arte, cultura y espectáculos","religión y credos","policía y justicia","deporte","weather","ciencia y tecnología","asuntos sociales","política","mano de obra","interés humano" ] },"entities" : { "columns": [[ "@BBCBreaking", 120],[ "Sydney", 103],[ "#sydneysiege", 68],[ "military police", 58],[ "#sydneyseige", 53],[ "National Security Committee", 51],[ "#SydneySiege", 34],[ "United States", 25],[ "Russia", 22],[ "#illridewithyou", 22],[ "#Sydney", 21],[ "#PeshawarAttack", 19],[ "Pakistan", 18],[ "#Peshawar", 15],[ "Commonwealth of Australia", 15],[ "@RT_com", 14],[ "@cnnbrk", 13],[ "Peshawar", 13],[ "Santa", 12],[ "Ferguson", 12],[ "@nabihahk", 10],[ "#mepolitics", 10],[ "#Randirobics", 10],[ "Tony Abbott", 9],[ "#Parents", 9],[ "@PaulNBlake", 9],[ "@nytimes", 9],[ "@DrLaryngeus", 8],[ "@BBCWorld", 8],[ "Apple", 8],[ "Isis", 8],[ "@BreakingNews", 8],[ "Martin Place", 8],[ "#Vegan", 7],[ "@CNN", 7],[ "#Pinterest", 7],[ "@ZahraBilloo", 7],[ "#Recipes", 7],[ "@pracca", 7],[ "#healthylifestyle", 7],[ "#Moms", 7],[ "Lindt", 7],[ "@chryslap", 6],[ "@KQEDedspace", 6],[ "Facebook", 6],[ "@nswpolice", 6],[ "@BBCNewsUS", 6],[ "@CNET", 6],[ "BBC", 6],[ "Hull", 6],[ "Sony", 6],[ "#Ferguson", 5],[ "@mariamsobh", 5],[ "@aashi__", 5],[ "@TheEconomist", 5],[ "Canada", 5],[ "@ThierryHenry", 5],[ "CIA", 5],[ "@DailyMirror", 5],[ "#boydbence", 5],[ "United Kingdom", 5],[ "@9NewsSyd", 5],[ "Instagram", 5],[ "London", 5],[ "@guardian", 5],[ "@cnewslive", 5],[ "@DailyMailAU", 5],[ "Putin", 5],[ "@cnni", 5],[ "New York", 5],[ "@Everton", 5],[ "@RMadridNation", 4],[ "@Randirobics", 4],[ "#lindtcafe", 4],[ "@WSJ", 4],[ "@Janelle", 4],[ "Kendall", 4],[ "Twitter", 4],[ "General Motors", 4],[ "Thierry Henry", 4],[ "Jo", 4],[ "Associated Press", 4],[ "@nspector4", 4],[ "@AP", 4],[ "@nsb2063", 4],[ "@PepperTheDog", 4],[ "Dios", 4],[ "@VancityBuzz", 4],[ "#Obesity", 4],[ "@m_wotherspoon", 4],[ "Wright", 4],[ "@Eagle_Child", 4],[ "@WorldRugby7s", 4],[ "Ebola", 4],[ "@ONENewsNZ", 4],[ "#9News", 4],[ "Obama", 4],[ "@AssignGuy", 4],[ "@Michaud2014", 4],[ "#Pakistan", 4],[ "ur", 4],[ "@TEDTalks", 4],[ "@UberFacts", 4],[ "@norwellfiredept", 4],[ "@FoxNews", 4],[ "@BreakngNewsPhtg", 3],[ "@Revenger210", 3],[ "@mattdpearce", 3],[ "@smh", 3],[ "@ElizabethMay", 3],[ "@TheDrunkStory", 3],[ "@Mahezabeen", 3],[ "@eirewalsh", 3],[ "@wheelbasecycles", 3],[ "@FootballFunnys", 3],[ "@MoreConsole", 3],[ "Singapore", 3],[ "@ABC", 3],[ "@FelixNater", 3],[ "#EFC", 3],[ "@pioneergirl08", 3],[ "#MartinPlace", 3],[ "@CityNews", 3],[ "@HAKRK", 3],[ "#BREAKING", 3],[ "@psychxdelic", 3],[ "#SCOTUS", 3],[ "Craig", 3],[ "@luisvicenteleon", 3],[ "#Kids", 3],[ "#AppleLive", 3],[ "@JamesBlunt", 3],[ "@BabyAnimalPics", 3],[ "James Blunt", 3],[ "@TheMeninism", 3],[ "Kenya", 3],[ "Ikea", 3],[ "World Cup", 3],[ "@NCIS_L_A_Fans", 3],[ "#Russia", 3],[ "@yonkersoem40", 3],[ "@History_Pics", 3],[ "Paul", 3],[ "FIFA", 3],[ "@9NewsAUS", 3],[ "@shahidkapoor", 3],[ "@fiskcg", 3],[ "#IllRideWithYou", 3],[ "Japan", 3],[ "Oliver", 3],[ "Mary", 3],[ "YouTube", 3],[ "@fizzer18", 3],[ "@DestinyNews_net", 3],[ "@itsadisaster", 3],[ "@uli_speck", 3],[ "@QishRashid", 3],[ "@Brittjabee", 3],[ "Tori Johnson", 3],[ "@CBCNews", 3],[ "@NetControl", 3],[ "@baltictraining", 3],[ "Donald", 3],[ "@NewTechCoppell", 3],[ "Europa", 3],[ "@WowEarthPics", 3],[ "@crisvalverdej", 3],[ "@trmyhre", 3],[ "South Africa", 3],[ "@RelatableQuote", 3],[ "@Bewickwren", 3],[ "@Independent", 3],[ "#Dubai7s", 3],[ "@SkyNewsBreak", 3],[ "#MyZeitgeist", 3],[ "@BuzzFeedNews", 3],[ "Michaud", 3],[ "Katrina Dawson", 3],[ "@MetroUK", 3],[ "#Fox25", 3],[ "@TechCrunch", 3],[ "@marelyndaniel", 3],[ "Max", 3],[ "#awesome", 3],[ "@BBCNewsAus", 3],[ "@BBCtrending", 3],[ "#BlackLivesMatter", 3],[ "@CNNMoney", 3],[ "America", 3],[ "#PeshawarSchoolAttack", 3],[ "Vivek Murthy", 3],[ "@em_ufsee", 3],[ "Pa.", 3],[ "@slvrfnx", 3],[ "#VCB12Days", 3],[ "@TAEVisionCEO", 3],[ "@lumiauk", 2],[ "@EconBizFin", 2],[ "@macinjosh", 2],[ "Crimean", 2],[ "@KCBGroup", 2],[ "#Cortana", 2],[ "#MichaelBrown", 2],[ "Sinclair", 2],[ "GHG", 2],[ "Starbucks Corporation", 2],[ "#Norwell", 2],[ "Morocco", 2],[ "@shebe86", 2],[ "@PantherZone", 2],[ "@MotherJones", 2],[ "@Reuters", 2],[ "#GreenSmoothies", 2],[ "Wallace", 2],[ "@ExportDevCanada", 2],[ "Black Mirror", 2],[ "@AlienTuna", 2],[ "@CityofChelseaPD", 2],[ "Mike", 2],[ "#ruble", 2],[ "New York Police Department", 2],[ "#OutFront", 2],[ "#COYB", 2],[ "@Sydell", 2],[ "@N_Fostell", 2],[ "@carolinemarcus", 2],[ "@PaulRieckhoff", 2],[ "@zoe231177", 2],[ "Cutler", 2],[ "@DustinGFitch", 2],[ "@CoalsonR", 2],[ "Norway", 2],[ "@LassoGuillermo", 2],[ "Atlanta", 2],[ "Adam", 2],[ "Alhamdulillah", 2],[ "Iraq", 2],[ "@tanjooilong", 2],[ "SSW", 2],[ "Leo", 2],[ "Oz", 2],[ "Everton", 2],[ "Justin Bieber", 2],[ "@Daily_Express", 2],[ "@slave2thefav", 2],[ "@Playdoughpoem", 2],[ "@cmanduley", 2],[ "@FootyHumour", 2],[ "Aristotle", 2],[ "Watson", 2],[ "East Millinocket", 2],[ "@TandonRaveena", 2],[ "Sydney CBD", 2],[ "@TIME", 2],[ "@engadget", 2],[ "KL", 2],[ "Orange", 2],[ "@russ008", 2],[ "@mindykaling", 2],[ "@TonyAbbottMHR", 2],[ "@CNNPolitics", 2],[ "@SincerelyTumblr", 2],[ "#ND", 2],[ "@UKenyatta", 2],[ "Cristiano Ronaldo", 2],[ "@EW", 2],[ "@manny_ottawa", 2],[ "@bonifacemwangi", 2],[ "@SPreyzner", 2],[ "Isaac", 2],[ "Starbucks", 2],[ "@cristilmethod", 2],[ "@TheCryptarch", 2],[ "@AnnaDegToGo", 2],[ "Selma", 2],[ "@Ants_SNEweather", 2],[ "@BPreyzner", 2],[ "#RealMadrid", 2],[ "@HistoryInPics", 2],[ "@2014_Neha", 2],[ "@IAVA", 2],[ "Ukraine", 2],[ "@transformers", 2],[ "@StevePhillips7", 2],[ "Ontario", 2],[ "@BuzzFeedOz", 2],[ "Denver", 2],[ "#GreeleyGrizwalds", 2],[ "@SoVeryBritish", 2],[ "New Zealand", 2],[ "#LastWords", 2],[ "@BBCSteveR", 2],[ "@DinaGusovsky", 2],[ "#Pes", 2],[ "#ClayHunt", 2],[ "Cheney", 2],[ "Chicago", 2],[ "Syria", 2],[ "@globeandmail", 2],[ "Giroud", 2],[ "@ReadInimicus", 2],[ "Ava", 2],[ "@CNBCFastMoney", 2],[ "@Bar_staff_probs", 2],[ "@PadreIsrael", 2],[ "Disney", 2],[ "Kyle", 2],[ "#healthyeating", 2],[ "#MartinPl", 2],[ "@TheRock", 2],[ "Truman", 2],[ "@KarinAlexander", 2],[ "#MTVStars", 2],[ "@pactcoffee", 2],[ "Bankia", 2],[ "@exp_juridico", 2],[ "@HamidMirGEO", 2],[ "Sydney Lindt", 2],[ "@FCBarcelona", 2],[ "Apple Watch", 2],[ "@christmas_clock", 2],[ "Mars", 2],[ "Allah", 2],[ "Atlético Tetuán", 2],[ "Jesus", 2],[ "@yogscast", 2],[ "Hague", 2],[ "Brand Ambassadors", 2],[ "@TuksFMNews", 2],[ "@__jolo", 2],[ "@MMP_Montana", 2],[ "@derprevere", 2],[ "Alaska", 2],[ "23 Standish Ave.", 2],[ "Top Cop", 2],[ "@neytauppa", 2],[ "@notcreative388", 2],[ "#Homeland", 2],[ "Philadelphia", 2],[ "Pearson", 2],[ "Walt Disney", 2],[ "@andersostlund", 2],[ "Christine", 2],[ "#Transformers", 2],[ "@ChrisKlemens", 2],[ "Amazon", 2],[ "@DattosDestiny", 2],[ "Press Trust of India", 2],[ "@JoeWMuchiri", 2],[ "ICYMI", 2],[ "@GabbyKaufman", 2],[ "Xbox One", 2],[ "Club World Cup", 2],[ "#SPOTY", 2],[ "Gaza", 2],[ "#mufc", 2],[ "@nonvitaltooth", 2],[ "@nytimesworld", 2],[ "#MakeItHappen", 2],[ "@9GAGTweets", 2],[ "#oil", 2],[ "@ShireenMazari1", 2],[ "@slang4201", 2],[ "@julieplec", 2],[ "@CNNSitRoom", 2],[ "@financialpost", 2],[ "#Australia", 2],[ "China", 2],[ "@ESPINOSAMCCANN", 2],[ "#HandsUpDontShoot", 2],[ "Joe", 2],[ "Christian", 2],[ "@NWDogRescue", 2],[ "@ArtturiArtturi", 2],[ "De Gea", 2],[ "@smebulok", 2],[ "@FriedmansJwlry", 2],[ "India", 2],[ "Franco", 2],[ "France", 2],[ "Diana", 2],[ "@lepage2014", 2],[ "Patrick", 2],[ "Ralph", 2],[ "Storm", 2],[ "Dawson", 2],[ "#Facebook", 2],[ "@GeoffNews", 2],[ "Barnes", 2],[ "#SydneyHostageCrisis", 2],[ "@BillNemitz", 2],[ "#Health", 2],[ "@KyleEvanReed", 2],[ "KFC", 2],[ "@DanaeBoyd", 2],[ "Johnny Abraham", 2],[ "Ferrari", 2],[ "@SimpsonsQOTD", 2],[ "#TeamPW", 2],[ "#martinplace", 2],[ "@azmemunyit", 2],[ "Rehman", 2],[ "@MrStevenGeorge", 2],[ "@MassStatePolice", 2],[ "@fromshadows", 2],[ "Malaysian Airlines", 2],[ "@johnkeypm", 2],[ "@DeeSet", 2],[ "@SETIInstitute", 2],[ "#AussieUnited", 2],[ "Scotland Yard", 2],[ "@MurtazaGeoNews", 2],[ "Leslie", 2],[ "Egypt", 2],[ "@ScotStreetStyle", 2],[ "@ManUtd", 2],[ "Chris", 2],[ "@SoTotallyToby", 2],[ "@lonelyplanet", 2],[ "South Korea", 2],[ "Lewis Hamilton", 2],[ "@arjastork", 2],[ "World Health Organization", 2],[ "Francis", 2],[ "@AneeRsyDney", 2],[ "Michael", 2],[ "@colinjevons", 2],[ "@NBCNews", 2],[ "Harper", 2],[ "@OutFrontCNN", 2],[ "@danny_macaskill", 2],[ "#COP20", 2],[ "@NYTNational", 2],[ "#tvd", 2],[ "@Newsweek", 2],[ "@HSBC_UK_Help", 2],[ "#bcpoli", 2],[ "Kevin", 2],[ "@lolasanya", 2],[ "Madrid", 2],[ "@MissMalini", 2],[ "Schiller", 2],[ "Britton", 2],[ "Ohio", 1],[ "@Rixpoet", 1],[ "#oops", 1],[ "@PumaBare", 1],[ "#PeterPanLive", 1],[ "#Education", 1],[ "@JonChevreau", 1],[ "@niwentweets", 1],[ "@CBSNews", 1],[ "#Science", 1],[ "@Laura_Figueroa", 1],[ "@Lisa_Wilkinson", 1],[ "@Sc0fy_", 1],[ "#FatherTed", 1],[ "@BroderickGreer", 1],[ "#Blood", 1],[ "Molana Fazal-u", 1],[ "@shaunwalker7", 1],[ "Pasir Ris", 1],[ "#Equines", 1],[ "@achufford", 1],[ "@FarahKhanAli", 1],[ "@BBCSPOTY", 1],[ "#brunch", 1],[ "@ThislsAmazing", 1],[ "@BungieInformer", 1],[ "@dpgushee", 1],[ "@richeisen", 1],[ "#YNWA", 1],[ "@TimOBrien", 1],[ "@mrewanmurray", 1],[ "@BarrilVenezuela", 1],[ "#Nutrition", 1],[ "Ahhh Sterling", 1],[ "@BradPittsPage", 1],[ "@GilletteStadium", 1],[ "@GuardianTT", 1],[ "#NeverFeltMoreLikeSingingtheBlues", 1],[ "Gary Neville", 1],[ "Brock Bottoms", 1],[ "@enzadesu", 1],[ "#firemission", 1],[ "#the24cookiesofChristmas", 1],[ "Legend Group", 1],[ "#womenarewatching", 1],[ "Santander", 1],[ "@challot_", 1],[ "Adrien Rabiot", 1],[ "@IBMoghadam", 1],[ "@3pm", 1],[ "@Arsenal", 1],[ "Investigation Team", 1],[ "Burnley", 1],[ "@FrankRGardner", 1],[ "Goodnight", 1],[ "@JRhodesPianist", 1],[ "@swogden10", 1],[ "@TPM", 1],[ "@abcnewsSydney", 1],[ "MTB", 1],[ "@MatthewPrescott", 1],[ "#Racism", 1],[ "@stocktraderwill", 1],[ "#AdoptDog", 1],[ "Harina", 1],[ "Asaad", 1],[ "Spain", 1],[ "@janengoiri", 1],[ "@RFU_RDO", 1],[ "International Airlines Group", 1],[ "#runs", 1],[ "Emilio Estevez", 1],[ "@andymientus", 1],[ "@htTweets", 1],[ "@kagtireema", 1],[ "Vladimir Putin", 1],[ "RNGesus", 1],[ "@matamoros_kathy", 1],[ "#FMRevolution", 1],[ "@JesseRoberts0n", 1],[ "@KBCoburn", 1],[ "#Nat", 1],[ "Romanian Revolution", 1],[ "@GearHeadz28", 1],[ "@FloydShivambu", 1],[ "@diaridtarragona", 1],[ "@falloutboy", 1],[ "@MobileBaySports", 1],[ "President @UKenyatta", 1],[ "Michael Grant", 1],[ "Dressed As Santa", 1],[ "@RBarkley20", 1],[ "@YourHistoryPics", 1],[ "Russell Brand", 1],[ "Rainmaker Files For Bankruptcy", 1],[ "@UmarCheema1", 1],[ "Capitol", 1],[ "Odell", 1],[ "GEO", 1],[ "#London's", 1],[ "@Bibliaenlinea", 1],[ "#CRomnibus", 1],[ "@blackrock", 1],[ "#EOD", 1],[ "@RTUKnews", 1],[ "Sana Mirza", 1],[ "Command Center", 1],[ "Business School", 1],[ "París", 1],[ "@Staleyphoto", 1],[ "Japan AND", 1],[ "@thomaspluck", 1],[ "@ciarale01", 1],[ "@Cristiano", 1],[ "Boston Police", 1],[ "@DannSahak", 1],[ "Acción Comunista", 1],[ "Andrew Cuomo", 1],[ "Sky Sports", 1],[ "#summertime", 1],[ "@deepikapadukone", 1],[ "Ferguson & Ebola", 1],[ "Ms Merkel Putin", 1],[ "@nytpolitics", 1],[ "#hurricane", 1],[ "Birthday Indiana", 1],[ "@ESPNStatsInfo", 1],[ "@ZachsMind", 1],[ "@1LeylaRodriguez", 1],[ "UncleMurda", 1],[ "Fav", 1],[ "@GrayConnolly", 1],[ "David Allen Ward", 1],[ "@A_D1su", 1],[ "@AFP", 1],[ "Zach Roerig", 1],[ "@Sportive23_", 1],[ "#foggytowin", 1],[ "@runnersworld", 1],[ "Maya Angelou", 1],[ "#climatechange", 1],[ "@SarahMillican75", 1],[ "@WMTWTV", 1],[ "#derisking", 1],[ "@ToxicFox", 1],[ "@your_screen_name", 1],[ "Caja Castilla-La Mancha", 1],[ "Waitin Fr", 1],[ "@Siva_Kartikeyan", 1],[ "Russian Central Bank", 1],[ "@almudenavigil", 1],[ "#god", 1],[ "Cove", 1],[ "Brian Lara", 1],[ "#KXL", 1],[ "@jerryagar1010", 1],[ "Harry", 1],[ "@Teespring", 1],[ "@OhMyHani", 1],[ "PTI", 1],[ "MNF", 1],[ "#REF", 1],[ "@VengeanceRacing", 1],[ "#wcvb", 1],[ "@MrActuary", 1],[ "Filipinas", 1],[ "Red Square", 1],[ "#environmentallyfriendly", 1],[ "@CiboMattoCiboMa", 1],[ "@ScienceBasedMed", 1],[ "MMO", 1],[ "@wjrothman", 1],[ "@DigitalLookNews", 1],[ "@Fareeloydias", 1],[ "@Truman_Black", 1],[ "@stephca", 1],[ "Mascot Challenge", 1],[ "@GidgetWA", 1],[ "With Admitted Former Crack Dealer Jay-Z", 1],[ "@RJSzczerba", 1],[ "@WBBMNewsradio", 1],[ "Lahoris", 1],[ "@therealcliffyb", 1],[ "@markondefense", 1],[ "@okothkenneth", 1],[ "@expansioncom", 1],[ "@GOP", 1],[ "#Christmasjumperday", 1],[ "@BBCTHREE", 1],[ "Dolly", 1],[ "MLK", 1],[ "@NYCCouncil", 1],[ "Betsy Smith", 1],[ "#hatesuffocatesprogress", 1],[ "@allkpop", 1],[ "Broadway & MacDonald St", 1],[ "@adamrichard", 1],[ "Telstra", 1],[ "@Dubai7s", 1],[ "@iScotNews", 1],[ "@baddyaddyy", 1],[ "@APHClarkson", 1],[ "@tariqmughal68", 1],[ "@ATLblog", 1],[ "Golden Globes", 1],[ "Angels Jannatul Firdos", 1],[ "@newtgingrich", 1],[ "#SeriouslyStrange", 1],[ "@kristenhare", 1],[ "Jamhuri Day", 1],[ "#Meograph", 1],[ "U2", 1],[ "@VIVErevista", 1],[ "#CristianoRonaldo", 1],[ "@morningmoneyben", 1],[ "@NBCSports", 1],[ "#MyZ", 1],[ "#EbolaResponse", 1],[ "23 Standish Street", 1],[ "#OffTheRecord", 1],[ "@nonstopwardle", 1],[ "TD", 1],[ "@jenanmoussa", 1],[ "@takouris", 1],[ "#Victory365", 1],[ "Saint Louis", 1],[ "@nationalpost", 1],[ "Megabus", 1],[ "Lingaa", 1],[ "@officialroycey", 1],[ "@KoinangeJeff", 1],[ "@bukorilaalamak", 1],[ "Adam Levines", 1],[ "#BOCapsule", 1],[ "Man Haron Monis", 1],[ "@TRobinsonNewEra", 1],[ "SC", 1],[ "Einsteins", 1],[ "@funnyortruth", 1],[ "Qu", 1],[ "RV", 1],[ "Torres", 1],[ "@nmcrooks", 1],[ "@DaveHaygarth", 1],[ "@sadiaacee", 1],[ "Google, Inc.", 1],[ "@brittanyr", 1],[ "@orestimusic", 1],[ "@MYSADCAT", 1],[ "Monty Python", 1],[ "@H0XH4", 1],[ "@chrisklemens", 1],[ "@ExUnitateVires", 1],[ "#LoneWolf", 1],[ "It Go", 1],[ "@DavidC516", 1],[ "@Gem_Davies", 1],[ "@londenbell", 1],[ "Statmnt Taliban", 1],[ "Iran", 1],[ "New Year", 1],[ "@BBCNewshour", 1],[ "@NewTechAoife", 1],[ "@jamestaylor20", 1],[ "Jesús", 1],[ "@Nkomati_", 1],[ "Nassau County Legislature", 1],[ "#TVDS6", 1],[ "@Bryan_Oviedo", 1],[ "@ULTA_Beauty", 1],[ "Petrobras", 1],[ "@Cher", 1],[ "#UQ", 1],[ "@RichardDawkins", 1],[ "Rory McIlroy", 1],[ "Man City", 1],[ "@TheSaucyFucker", 1],[ "#infosys", 1],[ "#Iglesia", 1],[ "Will Receive", 1],[ "PE", 1],[ "PD", 1],[ "#Kolchenko", 1],[ "@TonyPitchford", 1],[ "@aedurkin", 1],[ "Caroline @RiskAlert", 1],[ "Flippin", 1],[ "@DanceEatRepeat", 1],[ "#JamhuriDay", 1],[ "Afghanistan", 1],[ "@theIRC", 1],[ "Matt Dillon", 1],[ "OU", 1],[ "@WHO", 1],[ "Russ Feingold", 1],[ "@ErikaWCVB", 1],[ "BT Group", 1],[ "Discuss Police Policy", 1],[ "@CityNewsAmanda", 1],[ "Birth Vs. Kick", 1],[ "#YouthEmpowerment", 1],[ "@droblopuntoes", 1],[ "@cocaineprada", 1],[ "#PeshawarAttacks", 1],[ "@MahmoudRamsey", 1],[ "BUHARI", 1],[ "#Vancouver", 1],[ "@Canada_Business", 1],[ "Éric Cantona", 1],[ "PCLN", 1],[ "@TheRaDR", 1],[ "@President", 1],[ "@paulla", 1],[ "@rachaeljacobs", 1],[ "NY", 1],[ "@LeeannWright4", 1],[ "#News", 1],[ "Royal Albert Hall", 1],[ "#PrayForSydney", 1],[ "#Tech", 1],[ "@WhiteVsBlackTwt", 1],[ "Mo", 1],[ "Zuma", 1],[ "@poptartqueeen", 1],[ "@MaryamNSharif", 1],[ "@AwAKAning04", 1],[ "@KA_Gould", 1],[ "#MyRecruitBoard", 1],[ "@Official_NFFC", 1],[ "Ecuador", 1],[ "Newcastle United", 1],[ "Greta Garbo", 1],[ "New York St", 1],[ "@JLo", 1],[ "Caller", 1],[ "Eric Garner", 1],[ "@BleacherReport", 1],[ "#WIsen", 1],[ "Book Giveaway", 1],[ "@WFP", 1],[ "@SEIU", 1],[ "#KingHenry", 1],[ "ForeverStars", 1],[ "Pan Africanist Congress of Azania", 1],[ "Shoutout", 1],[ "@SkyNews", 1],[ "Mobocracy", 1],[ "Fbody Nation Kids", 1],[ "@NOD008", 1],[ "@paulapoundstone", 1],[ "@NPRNews", 1],[ "@newscomauHQ", 1],[ "Dietmar Hamann", 1],[ "Stone Cold Steve Austin", 1],[ "#iphone", 1],[ "Prince George", 1],[ "@codyk", 1],[ "@PiscesAreUs", 1],[ "WCSH", 1],[ "#6thcircuit", 1],[ "BBVA", 1],[ "@CP24", 1],[ "Citizens' Action Party", 1],[ "@forex_futures", 1],[ "Hotpot Supper Tickets", 1],[ "#HowToGetAwayWithMurder", 1],[ "LG", 1],[ "@voxdotcom", 1],[ "@OrchardGateway", 1],[ "@noaaocean", 1],[ "@jonathansamuels", 1],[ "@ricardo_hausman", 1],[ "@MercianRockyRex", 1],[ "Darth Vader", 1],[ "#money", 1],[ "@girlposts", 1],[ "@TanujVirwani", 1],[ "Josh", 1],[ "@stephenfry", 1],[ "21 Jump Street", 1],[ "@HackneyAbbott", 1],[ "@AnsarAAbbasi", 1],[ "#KyDerby140", 1],[ "NECBirmingham", 1],[ "@mediocredog", 1],[ "@dopesoph", 1],[ "@Scripture_Truth", 1],[ "#wouldyouaskaman", 1],[ "@SupraStrong_13", 1],[ "ToriJohnson", 1],[ "CNN", 1],[ "Haqqani", 1],[ "@LFCfamily5", 1],[ "#enzo", 1],[ "@akhilak", 1],[ "Aviva", 1],[ "@Capitancarloc", 1],[ "@sciencemuseum", 1],[ "APHClarkson", 1],[ "#evolvingcity", 1],[ "JV", 1],[ "@LtGovDuffyNY", 1],[ "@ntvkenya", 1],[ "@sosmaydan", 1],[ "Monaco", 1],[ "HAHAHA", 1],[ "@jaltucher", 1],[ "@BillMoyersHQ", 1],[ "@screenrant", 1],[ "OOOOOOOMG", 1],[ "CUTEEE", 1],[ "Fuji", 1],[ "@AdamSerwer", 1],[ "La Libertad", 1],[ "Nadia", 1],[ "@theedgemarkets", 1],[ "#icantbreathe", 1],[ "CMH", 1],[ "@dawn_com", 1],[ "Pacific", 1],[ "Pryor", 1],[ "@BFMradio", 1],[ "@Newsday", 1],[ "@DMiliband", 1],[ "#NH", 1],[ "Bloomberg", 1],[ "EEOC", 1],[ "@FT", 1],[ "Brendan", 1],[ "@Taranaki_NZ", 1],[ "England", 1],[ "@bostonpolice", 1],[ "#travel", 1],[ "Standish Ave.", 1],[ "Geo @MuaazAhsanGeo", 1],[ "@michaud2014", 1],[ "Gx", 1],[ "Miami", 1],[ "Aviva plc", 1],[ "Land", 1],[ "@dmardiste", 1],[ "Paul Revere", 1],[ "@larramalik", 1],[ "#suzesays", 1],[ "University of Valladolid", 1],[ "@ShiaPrincesss", 1],[ "Passenger Transport Authority", 1],[ "Podolski", 1],[ "#Fitness", 1],[ "VOIP", 1],[ "Pak Army", 1],[ "Malick", 1],[ "@qurratuzainudin", 1],[ "Angels", 1],[ "Wales", 1],[ "@Troll__Football", 1],[ "#SouthAfrica", 1],[ "@USARugby", 1],[ "#HealthIsPrimary", 1],[ "#tvds6", 1],[ "International Baccalaureate", 1],[ "#MeriBandook", 1],[ "@ABC7NY", 1],[ "St. Louis", 1],[ "@Waisale_Serevi", 1],[ "#Abbott", 1],[ "Matthew Bourne", 1],[ "@ystriya", 1],[ "@BBCSport", 1],[ "G20", 1],[ "#tcot", 1],[ "#gooner", 1],[ "#Runrunes", 1],[ "Surgeon General", 1],[ "@CoppellHigh", 1],[ "@BBCSporf", 1],[ "#Toronto", 1],[ "@JamesStewa", 1],[ "@flintbedrock", 1],[ "@LaylaaSays", 1],[ "@PRI", 1],[ "Gwen Moore", 1],[ "@Bu", 1],[ "@perlimaya", 1],[ "@nadeemmalik", 1],[ "@tufkaa", 1],[ "FA", 1],[ "Hmph", 1],[ "Overseas Sports Personality", 1],[ "Thundersnow", 1],[ "@jmcotelo", 1],[ "Missouri", 1],[ "#Hailstate", 1],[ "London Gatwick Airport", 1],[ "@LUADJeff", 1],[ "EW", 1],[ "@DTRubenIsrael", 1],[ "@msnbc", 1],[ "@BOCapsule", 1],[ "@Saj_PakPassion", 1],[ "@vikramchandra", 1],[ "#mcwccx", 1],[ "#addicted", 1],[ "PBA", 1],[ "@AsimBajwaISPR", 1],[ "@LFCTS", 1],[ "Banco Central de España", 1],[ "YTD", 1],[ "@AyseErinc", 1],[ "Mukherjee", 1],[ "@SocialRMadrid", 1],[ "American Psycho", 1],[ "Heathrow", 1],[ "@LauraBenanti", 1],[ "Cazorla", 1],[ "@HDNER", 1],[ "#NALS2014", 1],[ "Govt", 1],[ "@randybillings", 1],[ "Bill Powell", 1],[ "#IS", 1],[ "@bbcweather", 1],[ "@megynkelly", 1],[ "@MichaelaK33", 1],[ "@whereisnate", 1],[ "Steven #Naismith", 1],[ "@rockportbasset", 1],[ "#Angels", 1],[ "Earthquake", 1],[ "@Schuldensuehner", 1],[ "@AuburnJokes", 1],[ "@voguemagazine", 1],[ "Ian Supra", 1],[ "@wajih_sani", 1],[ "#CERT", 1],[ "FMT", 1],[ "@billshortenmp", 1],[ "Tom Coburn", 1],[ "@fijirugby", 1],[ "@HniaziISF", 1],[ "@Scott_Gilmore", 1],[ "@POLITICO", 1],[ "@CRonaldoFans15", 1],[ "@tweethutchy", 1],[ "#ManderaQuarryAttack", 1],[ "@TamaraMcCleary", 1],[ "@FatherTedSpeak", 1],[ "@BostonNewsMan", 1],[ "#Lindt", 1],[ "@pourmecoffee", 1],[ "Republican Bill Cassidy", 1],[ "#ISupportSanaMirza", 1],[ "Staveley", 1],[ "Jesé", 1],[ "CB", 1],[ "#NationalTrophy", 1],[ "Happy Home Company", 1],[ "#notimpressed", 1],[ "@WSJPolitics", 1],[ "@dailytelegraph", 1],[ "Al", 1],[ "@SCNosalMD", 1],[ "Loaded Baguette", 1],[ "@BuzzFeedIndia", 1],[ "At Sydney", 1],[ "Sydney Opera House", 1],[ "#MillionsMarchNYC", 1],[ "@ansarAAbbasi", 1],[ "BB", 1],[ "#Aliens", 1],[ "#thanksskipper", 1],[ "M'sian", 1],[ "@karrar_meer", 1],[ "@portalkritis", 1],[ "@SuzeOrmanShow", 1],[ "#EnviroIntel", 1],[ "@chrisshipitv", 1],[ "@TheFoxandCrown", 1],[ "@MaineDems", 1],[ "@atlblog", 1],[ "#magicalTuesday", 1],[ "@begumtothestars", 1],[ "@tdy_T", 1],[ "Reuters", 1],[ "@KCChiefs", 1],[ "@PurelyFootball", 1],[ "#Adopt", 1],[ "Thomas Howell", 1],[ "#food", 1],[ "PKR group", 1],[ "@EconEconomics", 1],[ "#Recruitment", 1],[ "@carlfogarty", 1],[ "#AllOfTheLights", 1],[ "#MerciThierry", 1],[ "#London", 1],[ "Racing de Avellaneda", 1],[ "Birmingham Crown Court", 1],[ "@thehill", 1],[ "Taliba", 1],[ "Far Cry", 1],[ "@DavidSchawel", 1],[ "Leinster Ploughing", 1],[ "#Ghent", 1],[ "Android", 1],[ "@EARMILK", 1],[ "#digitaldiplomacy", 1],[ "Germany", 1],[ "Hmm", 1],[ "@Metrorailinfo", 1],[ "Netflix, Inc.", 1],[ "Dania", 1],[ "Yorkshire", 1],[ "@ConfuciusPosts", 1],[ "@realmadriden", 1],[ "Big Bash", 1],[ "US Airways", 1],[ "@earthepix", 1],[ "#finishthejob", 1],[ "Champions League", 1],[ "#SYDNEYSIEGE", 1],[ "#UofA", 1],[ "Proud of Nassau Legis Dem Ldr", 1],[ "Dejan Lovren", 1],[ "Maine", 1],[ "Tilda Swinton", 1],[ "@CSPhotoscom", 1],[ "Sydney Cafe", 1],[ "@MtbSprocket", 1],[ "#snl", 1],[ "@AnaGtz79", 1],[ "#RussiaMeltdown", 1],[ "@Ashton5SOS", 1],[ "@ExcellentAnimal", 1],[ "#AsiaPacific", 1],[ "#pakistan", 1],[ "Dini", 1],[ "#Sentsov", 1],[ "#Live", 1],[ "@FJ0hana", 1],[ "@JWTelegraph", 1],[ "Banco Popular", 1],[ "#AMAs", 1],[ "@pretoriacoza", 1],[ "Mva Northborough", 1],[ "Talley", 1],[ "Empire State Building", 1],[ "@KTNKenya", 1],[ "@ObesityBlog", 1],[ "@HuffPostUKPics", 1],[ "@tom_harlock", 1],[ "Oohhhh", 1],[ "@Prem_S", 1],[ "Luis Enrique", 1],[ "Messi", 1],[ "@boohoo", 1],[ "@MailOnline", 1],[ "Sherlock", 1],[ "@FutbooIFichajes", 1],[ "@SputnikInt", 1],[ "@TheStrippin", 1],[ "Jakell Mitchell", 1],[ "#thesimpsons", 1],[ "@iamthekartel", 1],[ "Good", 1],[ "@BoniMtetezi", 1],[ "@BBCNewsAsia", 1],[ "#June27th", 1],[ "Geo @MurtazaGeoNews", 1],[ "LRT", 1],[ "#bikeracing", 1],[ "#Mirallas", 1],[ "#theKenyawewant", 1],[ "Wenger", 1],[ "@BrendonWu_", 1],[ "@BBCOS", 1],[ "@SunVoip", 1],[ "@Grand_Theatre", 1],[ "@ashsperls", 1],[ "#AN", 1],[ "Getty", 1],[ "#AL", 1],[ "#cupcake", 1],[ "@Brianmbunde", 1],[ "Cristiano", 1],[ "@EuromaidanPress", 1],[ "@ABCNewsLive", 1],[ "@Benogola", 1],[ "@bengollings10", 1],[ "The Sun", 1],[ "Eco", 1],[ "#sosingaporean", 1],[ "@azhairul", 1],[ "@broadwaycom", 1],[ "Tehrik-e-Taliban", 1],[ "#monash", 1],[ "#WorldAIDSDay", 1],[ "Madeleine McCann", 1],[ "La República", 1],[ "Nuh", 1],[ "First Family", 1],[ "@YYZemily", 1],[ "@thescript", 1],[ "#smartmoney", 1],[ "@Angieyy_", 1],[ "The New York Times Company", 1],[ "Lewis Craven", 1],[ "Man Utd", 1],[ "National Guard", 1],[ "Knn", 1],[ "Kot Radha Kishan", 1],[ "#fieldmarketing", 1],[ "@Oogwae", 1],[ "@MirrorRowZed", 1],[ "Venus", 1],[ "Fatou Bensouda", 1],[ "@FortuneMagazine", 1],[ "@SAMAATV", 1],[ "@ShiversDorhout", 1],[ "Lee Rigby", 1],[ "#pets", 1],[ "@Kevan_Abrahams", 1],[ "Optimus Prime & Bumblebee", 1],[ "#coffeehousecool", 1],[ "@tbhjuststop", 1],[ "@JessicaValenti", 1],[ "@MediaGhuru", 1],[ "@Baird", 1],[ "Sumatran", 1],[ "Chelsea Man Wanted", 1],[ "@banditocado", 1],[ "@QuadFins4Fun", 1],[ "@pdacosta", 1],[ "#econarchive", 1],[ "CycloCross Trophy Bradford", 1],[ "#ChristmasInWashington", 1],[ "@tmerilaht", 1],[ "@rioferdy5", 1],[ "In & Out Burger", 1],[ "@Winyy__", 1],[ "@sharmeenochinoy", 1],[ "@AGMuigai", 1],[ "@RaqiyahMays", 1],[ "Pakistan Taliban", 1],[ "#AFCvNUFC", 1],[ "@simonrademan", 1],[ "CNNgo", 1],[ "@bigboyja", 1],[ "#WhereTheMagicHappens", 1],[ "Darren Wilson", 1],[ "As Long As You", 1],[ "Wood & Steel", 1],[ "@mahezabeen", 1],[ "Woooh", 1],[ "#PolScotRecruit", 1],[ "@juliamacfarlane", 1],[ "Vine of Sen.", 1],[ "Palestine Bombings", 1],[ "Lord Saladin", 1],[ "Uncharacteristic", 1],[ "Mehmet Ozlap", 1],[ "#Space", 1],[ "#CrushT", 1],[ "John Ivison", 1],[ "@harristweedheb", 1],[ "North St. Paul", 1],[ "UberPop", 1],[ "@svarun_01", 1],[ "Waze", 1],[ "@VideosOfScience", 1],[ "@breakingbytes", 1],[ "@robjillo", 1],[ "#BelgiumSiege", 1],[ "@rebmatius", 1],[ "@UP_TownCenter", 1],[ "Aww", 1],[ "@WNYC", 1],[ "Cup Third Round trip", 1],[ "Metrolinx", 1],[ "@dfarmer14", 1],[ "#YearInSearch", 1],[ "@BBCLancashire", 1],[ "@JMLudes", 1],[ "@uscensusbureau", 1],[ "@D_DeGea", 1],[ "#Sydneysiege", 1],[ "@PBS", 1],[ "New South Wales", 1],[ "@Nanmanea", 1],[ "@eNCAnews", 1],[ "Petsmart", 1],[ "@JamilSmith", 1],[ "@ibieberlinear", 1],[ "Federal Reserve", 1],[ "#tosua", 1],[ "@Reu", 1],[ "@talyellin", 1],[ "@ChrChristensen", 1],[ "@Majid_Agha", 1],[ "Silent Nemo", 1],[ "@JackJackJohnson", 1],[ "@realDonaldTrump", 1],[ "@anonoMAN42", 1],[ "@TheCRonaldoFan", 1],[ "Bangkok", 1],[ "Kaddish", 1],[ "@latimes", 1],[ "@Jay_78_", 1],[ "@ProfJessieSmith", 1],[ "#PakSchoolSiege", 1],[ "@MyUNiDAYS", 1],[ "@YahoodiSaazish", 1],[ "@SpursOfficial", 1],[ "#DisneyOnBroadway", 1],[ "#Chiefs", 1],[ "Bublé", 1],[ "@HawksheadBrewer", 1],[ "@tlrd", 1],[ "Lahore", 1],[ "@OracKnows", 1],[ "@HuffPostUK", 1],[ "#G20Brisbane", 1],[ "Jagerbomb", 1],[ "Ask of You", 1],[ "@capricecrane", 1],[ "@WXII", 1],[ "@jehuegordon", 1],[ "Tesco", 1],[ "Hollywood", 1],[ "@GRlMDAREAPER", 1],[ "@philwcvb", 1],[ "@VisitNC", 1],[ "Matt Davis", 1],[ "Andalusian Party", 1],[ "Scarborough", 1],[ "Comcast", 1],[ "Rob Lowe", 1],[ "#productivity", 1],[ "@NewAmerica", 1],[ "@takiafaridah", 1],[ "#Dubai", 1],[ "@maryslandmovie", 1],[ "Songs of Innocence", 1],[ "@NYS_Ke", 1],[ "IBM", 1],[ "Cassian", 1],[ "@lynnOnCrime", 1],[ "@meganamram", 1],[ "@TomCoburn", 1],[ "Nicolae Ceau", 1],[ "@RoomeeTimes", 1],[ "@UpshotNYT", 1],[ "Ray Lewis", 1],[ "#adoptable", 1],[ "Nome", 1],[ "#alaric", 1],[ "Seventh Avenue", 1],[ "@Contentions", 1],[ "Muslim Community", 1],[ "#thankful", 1],[ "Harina Pan", 1],[ "Arc", 1],[ "Banco Santander", 1],[ "@LaundyCraigMP", 1],[ "@STERLINGMHOLMES", 1],[ "@Mobkay", 1],[ "Jeez", 1],[ "Kiska Volcano", 1],[ "@kdastgirkhan", 1],[ "@EngadgetUK", 1],[ "@NHDavies13", 1],[ "@BoxOfficeMexico", 1],[ "#illridewithTori", 1],[ "#tweet4taiji", 1],[ "Acción Católica", 1],[ "@mencap_charity", 1],[ "@yourfamilydoc", 1],[ "Mississippi St", 1],[ "@WladimirZanoni", 1],[ "#carrotforacock", 1],[ "@AlyssaCRaley", 1],[ "#Montgomery", 1],[ "#KyDerby", 1],[ "George Stinney", 1],[ "#AdoptCat", 1],[ "@AshleySiegs", 1],[ "#medwomen", 1],[ "Servicio de Atención a las Víctimas de delitos violentos", 1],[ "Weekly Nightfall", 1],[ "#Cat", 1],[ "Polo Sweet Bag", 1],[ "Camille Cosby", 1],[ "COPS", 1],[ "@TheSimpsons", 1],[ "#Hull", 1],[ "Virat Kohli", 1],[ "@JennyWCVB", 1],[ "@MMViverito", 1],[ "@Canada", 1],[ "@Ziya_Meral", 1],[ "Barbie", 1],[ "CRISTIANO RONALDO PORTUGAL", 1],[ "Housing Unit", 1],[ "#CHISpaVan", 1],[ "@albinlilas", 1],[ "Parakas", 1],[ "Sneijder", 1],[ "@CarolCNN", 1],[ "LDP", 1],[ "West St. Paul", 1],[ "@StefSimanowitz", 1],[ "@jarelkun", 1],[ "#AmericanHorrorStory", 1],[ "@business", 1],[ "SHVETSOV", 1],[ "@TheRunningBug", 1],[ "Sydney Morning Herald", 1],[ "#DENSI", 1],[ "Military Intelligence, Section 5", 1],[ "@SammyTellem", 1],[ "@elblogsalmon", 1],[ "@ohimsosure", 1],[ "Bay Area", 1],[ "AmerUs Group", 1],[ "Gov't", 1],[ "Ballon", 1],[ "#FieldMarketing", 1],[ "@LiamGillham93", 1],[ "Humboldt County", 1],[ "Kar", 1],[ "@BilldeBlasio", 1],[ "#Cyclocross", 1],[ "M.Serraller", 1],[ "#boydbe", 1],[ "@CallyGingrich", 1],[ "@IEPI_ecuador", 1],[ "@bronwen", 1],[ "Rail Fun Day", 1],[ "Greg", 1],[ "@GoalUK", 1],[ "#Entertainment", 1],[ "#DerechosHumanos", 1],[ "@KenyaPower", 1],[ "Pervsis", 1],[ "Julio Jones", 1],[ "@HolidayInn", 1],[ "#26", 1],[ "Police Se", 1],[ "#MateShip", 1],[ "@DogsTrust", 1],[ "@SkyBet", 1],[ "@howardlindzon", 1],[ "Cairo", 1],[ "@newtechrebekahp", 1],[ "Kiev", 1],[ "#FarmMurders", 1],[ "Greeley", 1],[ "@Fred_Delicious", 1],[ "PIXXX", 1],[ "@HeathrowAirport", 1],[ "@LBoucher77", 1],[ "#15", 1],[ "@DBessClass", 1],[ "Ma Rte", 1],[ "@Channel9", 1],[ "@yanchooow", 1],[ "@CTVVancouver", 1],[ "@VirginTrains", 1],[ "@guardian_sport", 1],[ "Deputy Commissioner Catherine Burn", 1],[ "#FallOutBoyABAP", 1],[ "@NYCEMSwebsite", 1],[ "@kunalkohli", 1],[ "East Pakistan", 1],[ "Pearson Educación España", 1],[ "@FIFAcom", 1],[ "@supcollins", 1],[ "Panther Nation", 1],[ "@DLoesch", 1],[ "@SunnyLeone", 1],[ "@CA2015", 1],[ "Pelham NH", 1],[ "#EastEnders", 1],[ "@ezralevant", 1],[ "#welikemike", 1],[ "BETTA BRENCH", 1],[ "Dodgeball", 1],[ "@SelfieNigga", 1],[ "@BabyAnimalGifs", 1],[ "#Nassau", 1],[ "Tesco Corporation", 1],[ "@Instagram", 1],[ "Anushka Sharma", 1],[ "#Competition", 1],[ "@MIRAMETV", 1],[ "Paris Saint-Germain Football Club", 1],[ "#vietnambelievable", 1],[ "Tmn Tun Dr Ismail", 1],[ "Tom Cruise", 1],[ "@BN247", 1],[ "Harris Tweed", 1],[ "#CongressInOneWord", 1],[ "@JuliaDavisNews", 1],[ "@wbir", 1],[ "Bangladesh", 1],[ "@sehunsqueen", 1],[ "@downriver_b", 1],[ "@INTHENOWRT", 1],[ "#THFC", 1],[ "Male", 1],[ "@GrangerKate", 1],[ "@etribune", 1],[ "United Arab Emirates", 1],[ "#PTI", 1],[ "@ALcomMobile", 1],[ "@ATHE1STP0WER", 1],[ "@ClaireaBellaLtd", 1],[ "Mugshot of Michael Crooker", 1],[ "Gerald Kaufman", 1],[ "@SaifRRahman", 1],[ "@SenFeinstein", 1],[ "@Iamksgofficial", 1],[ "Cali", 1],[ "Residual Value Awards", 1],[ "Google Zeitgeist", 1],[ "Digital Crown", 1],[ "Lions", 1],[ "Narendra Modi", 1],[ "SabahUS Dollar", 1],[ "Ahh", 1],[ "@Talkmaster", 1],[ "#Showtime", 1],[ "@Know", 1],[ "@itvnews", 1],[ "#Finally", 1],[ "Liverpool", 1],[ "Kansas", 1],[ "#Wellness", 1],[ "@liptika_", 1],[ "@AshmanAmirudin", 1],[ "@huntersbayradio", 1],[ "@Kimmyincali", 1],[ "@AsliHaroon", 1],[ "#Sweeps", 1],[ "@PPMEAF", 1],[ "Make Your Own Double Helix Xmas Tree", 1],[ "Channel 4", 1],[ "Upton", 1],[ "@BBCNews", 1],[ "The Museum", 1],[ "@TheAnonMessage", 1],[ "#Mencap", 1],[ "@Vnmol", 1],[ "#workinghours", 1],[ "Rhode Island", 1],[ "#OviedoBaby", 1],[ "@StandardIssueUK", 1],[ "Mark Owen", 1],[ "CM Balochistan", 1],[ "@RussOnPolitics", 1],[ "@NerdyWonka", 1],[ "#HA1LSTATE", 1],[ "@UkraineReddit", 1],[ "@CruzRojaEsp", 1],[ "@K_Simmz", 1],[ "#genius", 1],[ "@KimKardashian", 1],[ "@NewsHour", 1],[ "@HuffingtonPost", 1],[ "@CBSFantasy", 1],[ "#GiftGorgeously", 1],[ "@m_cof", 1],[ "LDMBA", 1],[ "#KentuckyDerby", 1],[ "#bbcqt", 1],[ "Aamilah", 1],[ "@google", 1],[ "Pro Sc", 1],[ "Julie", 1],[ "@fasiranjha", 1],[ "@bobatl", 1],[ "Brazil", 1],[ "#alwayswelcome", 1],[ "@YourAnonNews", 1],[ "@studentawards", 1],[ "Fernando Soto Rojas", 1],[ "@RaissaAlmanda", 1],[ "@James_Baltic", 1],[ "@Cookstar118", 1],[ "@SuccessfulIy", 1],[ "@MaajidNawaz", 1],[ "Roundup", 1],[ "@Coppellisd", 1],[ "#l", 1],[ "#FindingDory", 1],[ "@VisitLancashire", 1],[ "@AdrianaStuijt", 1],[ "Fort Lauderdale", 1],[ "#g", 1],[ "@SoSingaporean", 1],[ "High", 1],[ "@KenyaRedCross", 1],[ "@iamwill", 1],[ "la Caixa", 1],[ "@JODYHiGHROLLER", 1],[ "Liverpool F. C.", 1],[ "Ebola-hit West Africa", 1],[ "#VIRAL", 1],[ "#Kenya", 1],[ "@ArupThoughts", 1],[ "@runzourry", 1],[ "@twirlyswirly", 1],[ "#Scanning", 1],[ "Señor", 1],[ "Chris Brown", 1],[ "#marriage", 1],[ "Samsung Gear", 1],[ "Springarab", 1],[ "@SenateDems", 1],[ "#BCPo", 1],[ "#PatriotsNation", 1],[ "@grenouf", 1],[ "@SteveMarshallNZ", 1],[ "#NOAA", 1],[ "#2", 1],[ "@NickHanauer", 1],[ "@stalemt", 1],[ "Sky News Australia", 1],[ "@PickeringTj", 1],[ "#Scandal", 1],[ "@RealPaulWalker", 1],[ "#Taliban", 1],[ "#Chile2015", 1],[ "@KathyHochul", 1],[ "@jennablan", 1],[ "#ableg", 1],[ "Marca", 1],[ "KingHenry", 1],[ "Google Maps", 1],[ "Gracias Cristi", 1],[ "The hotel", 1],[ "Louisiana Democratic Sen.", 1],[ "@ShoeMeCA", 1],[ "#MH370", 1],[ "@chrisgailus", 1],[ "Justin", 1],[ "@MikeFriday09", 1],[ "@SCC_Barcelona", 1],[ "Alan", 1],[ "#Brazil", 1],[ "@LFC", 1],[ "Steve Young", 1],[ "@NewsOnTheMin", 1],[ "@Prevent_Obesity", 1],[ "#Radio", 1],[ "@ldbene10", 1],[ "@tanehisicoates", 1],[ "Saskatchewan", 1],[ "@awkwardposts", 1],[ "@Business", 1],[ "@gst183", 1],[ "Jani", 1],[ "#PLL", 1],[ "#EBOLA", 1],[ "@JackDromeyMP", 1],[ "GOTV", 1],[ "@TheDailyEdge", 1],[ "King Henry", 1],[ "ENIPLA", 1],[ "#Eyecon", 1],[ "Daily Sabah", 1],[ "@arjunk26", 1],[ "#AUBvsMSST", 1],[ "Panic", 1],[ "@saks", 1],[ "#DoNowFerguson", 1],[ "@TEDxBeaconSt", 1],[ "@NOAA", 1],[ "Cruz Azul", 1],[ "#askfast", 1],[ "@jimpoco", 1],[ "#OneNightStand", 1],[ "#gamergate", 1],[ "@MetPoliceUK", 1],[ "@SHO_Homeland", 1],[ "@SteaknShake", 1],[ "@comcast", 1],[ "@alsmiffy", 1],[ "@usgs", 1],[ "Hillary Clinton", 1],[ "@ComedyOrTruth", 1],[ "#inspiration", 1],[ "Izquierda de Cataluña", 1],[ "@jimmyfallon", 1],[ "@Reverend_Scott", 1],[ "@NelsonBocaranda", 1],[ "#PUSKAS", 1],[ "Stream of the Lindt Cafe", 1],[ "@CNBC", 1],[ "#IAmMyKenya", 1],[ "#BearGrylls", 1],[ "@SkySportsNewsHQ", 1],[ "Frank Sinatra", 1],[ "Massachusetts", 1],[ "#TrayvonMartin", 1],[ "@NewsHourExtra", 1],[ "David Suzuki", 1],[ "@newtechmorgan", 1],[ "Carrà", 1],[ "@NicolasMaduro", 1],[ "Happy Endings", 1],[ "@mehransanam", 1],[ "@CNNOpinion", 1],[ "Florida", 1],[ "@kaytazb", 1],[ "#FMRevoluti", 1],[ "@nickconfessore", 1],[ "@MountVernon", 1],[ "the Guardian", 1],[ "@WkyJoven", 1],[ "@AlexBrown77", 1],[ "@AnneWaiguru", 1],[ "Champions League Last", 1],[ "@_evafox", 1],[ "@TalatHussain12", 1],[ "B'way", 1],[ "@LBC", 1],[ "@TheWilsonCenter", 1],[ "Corel Draw", 1],[ "@RamzZy_", 1],[ "@PTXofficial", 1],[ "#fox25", 1],[ "@BookOProverbs", 1],[ "Roku", 1],[ "@KyivPost", 1],[ "Chile", 1],[ "#SkyBetTransferFund", 1],[ "@ShangriLa_Van", 1],[ "@WSJAsia", 1],[ "@hitRECord", 1],[ "@Battle", 1],[ "@XboxQwik", 1],[ "Gauteng", 1],[ "#EricGarner", 1],[ "Crimea", 1],[ "OHMAIGOD", 1],[ "@HaseenaAtomBum", 1],[ "@AnupKaphle", 1],[ "#Northboro", 1],[ "Game of Thrones", 1],[ "McPherson Square & L'Enfant Plaza", 1],[ "Oprah", 1],[ "#PoliceState", 1],[ "@ImBossyBoots", 1],[ "#TopDocNow", 1],[ "#Hersheys", 1],[ "Aqib Talib", 1],[ "Surveys of Mars", 1],[ "@imVkohli", 1],[ "@TheScotsman", 1],[ "Federal Reserve System", 1],[ "#climateaction", 1],[ "lesbian gay bisexual/pansexual and transgender people", 1],[ "@Julius_S_Malema", 1],[ "Simon Harris", 1],[ "Best Music", 1],[ "#CHRISTMAS DAY", 1],[ "@paulhicks63", 1],[ "#Sevens", 1],[ "@KayBurley", 1],[ "@RiteExpressions", 1],[ "Randirobics Galactic Gazette", 1],[ "@Gaetano_lo_hace", 1],[ "@NYCGreenfield", 1],[ "#Malaysia", 1],[ "@BBCr4today", 1],[ "Uber", 1],[ "@yv", 1],[ "@newsday", 1],[ "@MayaLand3", 1],[ "#CHRISTMAS", 1],[ "En12", 1],[ "Ferguson Missouri", 1],[ "@TheWorldImages", 1],[ "@troyesivan", 1],[ "#OrangeIsTheNewBlack", 1],[ "@ReutersLatam", 1],[ "@Ghetto_F0X", 1],[ "7News", 1],[ "Sheena", 1],[ "@TheLadBible", 1],[ "@CoveGuardians", 1],[ "@Bellows4Senate", 1],[ "@Nashgrier", 1],[ "@HouseofCards", 1],[ "@atiku", 1],[ "@MKB1A", 1],[ "#Bradford", 1],[ "Amal Clooney", 1],[ "@nicolasmsarries", 1],[ "@English_AS", 1],[ "@Joey_Del", 1],[ "#Crimea", 1],[ "@kids_exercise", 1],[ "Walford", 1],[ "@sailorkilljoy_", 1],[ "@l0lbac0n", 1],[ "@GAVI", 1],[ "@PzFeed", 1],[ "Lion", 1],[ "Most Popular Searches On Google In", 1],[ "@Tempibones", 1],[ "John Crawford", 1],[ "@GregSmithMD", 1],[ "@kashf7sab", 1],[ "@ScanBC", 1],[ "@BanuBCicek", 1],[ "@Mannam_92", 1],[ "París Saint Germain", 1],[ "one fucked up place", 1],[ "Reuters Opinion Strobe Talbott", 1],[ "@PLASTICPLATES", 1],[ "@LogitechG", 1],[ "@grg", 1],[ "#RWWinterWeek", 1],[ "#RugbySevens", 1],[ "Surkov Lt", 1],[ "#burnout", 1],[ "@moody", 1],[ "#Foot", 1],[ "@kravsazzle", 1],[ "@MockMavPam", 1],[ "@RosalieBardo", 1],[ "#matt", 1],[ "#BenStiller", 1],[ "#GTHOM", 1],[ "@KingdomWildlife", 1],[ "#SouthSudan", 1],[ "Rio de Janeiro", 1],[ "Howard Schultz", 1],[ "Pslam", 1],[ "Cosby", 1],[ "Department of Corrections", 1],[ "@gedikaslihan", 1],[ "Afric", 1],[ "African Union", 1],[ "El Nido", 1],[ "#AAFPNCCL", 1],[ "@ProBirdRights", 1],[ "James Altucher", 1],[ "@news_va_es", 1],[ "@brithume", 1],[ "@nikicheong", 1],[ "Orlando", 1],[ "#ReyesparaTodos", 1],[ "Rachel", 1],[ "Queens Park Rangers", 1],[ "Hero", 1],[ "Lima", 1],[ "President Uhuru Kenyatta", 1],[ "Holiday", 1],[ "@IMAXSOFL", 1],[ "El Salvador", 1],[ "#Blackpool", 1],[ "@Tim_Ste", 1],[ "@RD_Economist", 1],[ "@FtLauderdaleSun", 1],[ "Nigeria", 1],[ "@Marcasur", 1],[ "#ParksAndRec", 1],[ "#news", 1],[ "@sonamakapoor", 1],[ "@intelwire", 1],[ "Benjamin Franklin", 1],[ "#Indiawithpakistan", 1],[ "@EliotCutler", 1],[ "@nyonair", 1],[ "Beenie Man", 1],[ "Camille", 1],[ "@southernsnowgal", 1],[ "@foofighters", 1],[ "@jesserbnwtz", 1],[ "@Skrillex", 1],[ "@nytimesbooks", 1],[ "Bill", 1],[ "@rarestcat", 1],[ "@DFWscanner", 1],[ "@southsalem", 1],[ "@GaryLineker", 1],[ "@fox25news", 1],[ "@bipsluvurself", 1],[ "@backstreetboys", 1],[ "@LadySandersfarm", 1],[ "@GetTwistedRecs", 1],[ "Belgium", 1],[ "everton @RBarkley20", 1],[ "@toughlovemusic", 1],[ "#TheLeftovers", 1],[ "#SpreadLove", 1],[ "@oaarchitects", 1],[ "Valencia", 1],[ "@AmiriKing", 1],[ "#corvette", 1],[ "HBO", 1],[ "#Mandera", 1],[ "@washingtonpost", 1],[ "@AllisterHeath", 1],[ "@KrisPoB", 1],[ "@TalatHussain", 1],[ "#chinesetakeaway", 1],[ "@ReutersBiz", 1],[ "@SundayBrunchC4", 1],[ "@OilsandsAction", 1],[ "Annual Shop", 1],[ "@mathi8888", 1],[ "#Drones", 1],[ "Google", 1],[ "ULTA", 1],[ "#MAtraffic", 1],[ "@anirudhofficial", 1],[ "Weather Bomb", 1],[ "Olympia", 1],[ "#TierraDeMaría", 1],[ "Steve Bell", 1],[ "@mubasherlucman", 1],[ "@bbcworldservice", 1],[ "@KazimAlam", 1],[ "London Bridge", 1],[ "@Jess_Baltic", 1],[ "@SkyNewsAu", 1],[ "@njiiru", 1],[ "@craigadams49", 1],[ "#z06", 1],[ "@Express_Pics", 1],[ "@MASCA_National", 1],[ "#ISIS", 1],[ "nueva moto", 1],[ "California", 1],[ "@Ayeshatakia", 1],[ "#books", 1],[ "@NatGeo", 1],[ "Tottenham Hotspur", 1],[ "@freedomtomarry", 1],[ "#Gillette", 1],[ "@judmoo", 1],[ "#PassItOn", 1],[ "@hitRECordJoe", 1],[ "@LinusKaikai", 1],[ "@JulesBistro", 1],[ "@rezaaslan", 1],[ "Courtesy Marco Hartz", 1],[ "@BJPLucknowBJP", 1],[ "@Prophecy_YEC", 1],[ "#SaksHoliday", 1],[ "@BBCYaldaHakim", 1],[ "#recruitment", 1],[ "Kenya Navy", 1],[ "Frisco Melt", 1],[ "Putins", 1],[ "@DeleMomodu", 1],[ "GENE KELLY", 1],[ "@ernestorileyita", 1],[ "@siberianluck", 1],[ "Dallas", 1],[ "Metro-Goldwyn-Mayer Incorporated", 1],[ "@TheEllenShow", 1],[ "@analitica", 1],[ "Travis Kelce", 1],[ "@ARothNYT", 1],[ "@MrMichaelSpicer", 1],[ "STFU", 1],[ "Vietnam", 1],[ "America Herald", 1],[ "Moulin", 1],[ "@maddow", 1],[ "#SoulOnFire", 1],[ "Wilson Airport", 1],[ "No Bake Chocolate Cookies", 1],[ "Ridley Scott", 1],[ "@mckenzierose", 1],[ "Red Crescent Islamabad", 1],[ "@TDR_Network", 1],[ "@FairQuestions", 1],[ "@INTLSpectator", 1],[ "@TroyAikman", 1],[ "Jan", 1],[ "Korean War", 1],[ "#CapitalPunishmentForTTP", 1],[ "#MPAC14", 1],[ "@BlogApprentice", 1],[ "Awuor", 1],[ "Kentmere", 1],[ "@cathy_macdonald", 1],[ "@LaOpcionV", 1],[ "#underwaterhousing", 1],[ "Enfield", 1],[ "#Preparedness", 1],[ "Gervinho", 1],[ "#KConmymind", 1],[ "@va_va_vati", 1],[ "Punjab", 1],[ "#siegeselfie", 1],[ "@ThaPrinceTaylor", 1],[ "@svcred", 1],[ "Eurobank del Mediterráneo", 1],[ "@KAUSHALVYAS23", 1],[ "#raise", 1],[ "@JimmyVielkind", 1],[ "#Newsday", 1],[ "@JohnMbadi", 1],[ "@depericias", 1],[ "@NewEarthquake", 1],[ "@astroehlein", 1],[ "@PhxKen", 1],[ "#YogscastJingleJam", 1],[ "@ChiefsReporter", 1],[ "@erikagparas", 1],[ "@iamthatgirl", 1],[ "Blackboard, Inc.", 1],[ "#brandmanagement", 1],[ "#Destiny's", 1],[ "#sy", 1],[ "@Naira_TVD", 1],[ "#powermatters", 1],[ "#LittleGlobalCitizen", 1],[ "Australia PM", 1],[ "@meredithfrost", 1],[ "#GodBless", 1],[ "Based Telescope", 1],[ "@UCWNews", 1],[ "@CanariasZEC", 1],[ "Tenerife", 1],[ "@BenjaminNorton", 1],[ "With Fries", 1],[ "@LocatScotland", 1],[ "@JONWEXFORD", 1],[ "Malaysians", 1],[ "Sunset Overdrive", 1],[ "@MethuenPolice", 1],[ "@seb9011", 1],[ "@nz7s", 1],[ "Bugis Street", 1],[ "@jamtfe", 1],[ "@MyRecruitBoard", 1],[ "@Chelsea_Goulden", 1],[ "Chris de Burgh", 1],[ "Optus", 1],[ "#heartbroken", 1],[ "@GradElitism", 1],[ "#WCVB", 1],[ "@policescotland", 1],[ "#notankers", 1],[ "@kunalnayyar", 1],[ "@rtked", 1],[ "Pit", 1],[ "#EconomicDecline", 1],[ "#EggBowl2014", 1],[ "#putoutyourbats", 1],[ "@tkelce", 1],[ "@PoderJudicialEs", 1],[ "@splcenter", 1],[ "Eskom", 1],[ "#project543", 1],[ "Pic", 1],[ "WWE", 1],[ "@Markthewise", 1],[ "@shafidpk", 1],[ "@Crossfire", 1],[ "@AlertZaAfrica", 1],[ "@BBCNewsnight", 1],[ "@OwenBennettJone", 1],[ "#macaroons", 1],[ "Erdogan", 1],[ "@CivGame", 1],[ "@ScienceFuture1", 1],[ "#humans", 1],[ "Port Elizabeth", 1],[ "#suicide", 1],[ "Rude", 1],[ "@realmadrid", 1],[ "DID DE GEA", 1],[ "@SanaMerza", 1],[ "RM10k", 1],[ "@AnupamPkher", 1],[ "Pattie", 1],[ "@CNNFC", 1],[ "Ken Okoth", 1],[ "@Jordanems", 1],[ "#Balochistan", 1],[ "@staronline", 1],[ "Malala Yousafzai", 1],[ "Alabama", 1],[ "#volcano", 1],[ "Freshies", 1],[ "Barakah", 1],[ "@03gibbss", 1],[ "#Pisces", 1],[ "#icanshowyoutheworld", 1],[ "#XboxOne", 1],[ "@JavedAzizKhan", 1],[ "Balotelli", 1],[ "@ReutersUS", 1],[ "#wontbelongnow", 1],[ "Wes Welker", 1],[ "Yung Chunky", 1],[ "@BloombergNews", 1],[ "Spotify", 1],[ "@TelegraphPics", 1],[ "@HSBC_Rugby", 1],[ "Imran Khan", 1],[ "NBN", 1],[ "@ChrisReason7", 1],[ "@sierraboggess", 1],[ "@sheridanvoysey", 1],[ "@Stoked4Saturday", 1],[ "Young Pak Arm", 1],[ "#trending", 1],[ "#yogjam", 1],[ "@NATSPressOffice", 1],[ "Shenna", 1],[ "Edge Markets", 1],[ "@PastorTullian", 1],[ "#samoa", 1],[ "@SmahmoodS", 1],[ "#Gamers", 1],[ "@AbabuNamwamba", 1],[ "Novorossia", 1],[ "@ecuavisa", 1],[ "Cameron Mackintosh", 1],[ "@HennaK5", 1],[ "#GraciasMas", 1],[ "@sweatitoutmus", 1],[ "Lionsgate", 1],[ "@marcmarquez93", 1],[ "Hit Medley", 1],[ "Jamaica", 1],[ "@BenThomasPreps", 1],[ "@MarcSchwieger", 1],[ "@fpinvesting", 1],[ "@AsiaPacNews", 1],[ "@EntMagazine", 1],[ "@LOLGOP", 1],[ "@Declaracion", 1],[ "Mike Brown", 1],[ "@ec", 1],[ "#lp", 1],[ "Dogs Only", 1],[ "#HumanityRestored", 1],[ "@GovChristie", 1],[ "Pablo Ruz", 1],[ "Magreb", 1],[ "@russian_market", 1],[ "@Rockettes", 1],[ "#Northeas", 1],[ "#NCISLA", 1],[ "Held In Downtown Sydney Cafe", 1],[ "Marruecos", 1],[ "@FinnWittrock", 1],[ "@KPilkingtonQ", 1],[ "@iambohemia", 1],[ "Navidad", 1],[ "@deepali_shree", 1],[ "Our War", 1],[ "@_cassian", 1],[ "Dunya News", 1],[ "#PakistanSiege", 1],[ "Connection With Double Shooting", 1],[ "Yus", 1],[ "Ex-Dewey Partner", 1],[ "@mradamscott", 1],[ "RM10", 1],[ "Anderlecht", 1],[ "Liga de Fútbol Profesional", 1],[ "Pretyy", 1],[ "@PleasureEllis", 1],[ "@Abogacia_es", 1],[ "@OilandGasInvest", 1],[ "Shah Alam", 1],[ "Van Ruymbeke", 1],[ "Loving You", 1],[ "#xfactor", 1],[ "Lear Corporation", 1],[ "Hatttte", 1],[ "Wetten Dass", 1],[ "Container Khan", 1],[ "Rubio", 1],[ "@FrTedQOTD", 1],[ "@judz5", 1],[ "@nbc6", 1],[ "Ameen", 1],[ "@markchampkins", 1],[ "@Brilliant_Ads", 1],[ "Kitchen Nightmares", 1],[ "Prime Minister Tony Abbott", 1],[ "@urjc", 1],[ "Granddaddy", 1],[ "@BarackObama", 1],[ "Child Inn", 1],[ "@LOLsuren", 1],[ "@greta", 1],[ "@Glinner", 1],[ "@DanielGruchy", 1],[ "@scsj", 1],[ "@CBSShowbiz", 1],[ "@jimsciutto", 1],[ "Young Men's Christian Association", 1],[ "Pfft", 1],[ "Mary Landrieu", 1],[ "Ay Chiamo", 1],[ "Leo Messi", 1],[ "@INdnrnews", 1],[ "Cheryl", 1],[ "Allah SWT", 1],[ "@BTUpdates", 1],[ "@PaulMerrillWMTW", 1],[ "@krissybri", 1],[ "@saxenavishakha", 1],[ "@BradFrenette", 1],[ "#LFC", 1],[ "@ReutersLive", 1],[ "@MCHammer", 1],[ "#mateship", 1],[ "Shaun Lander", 1],[ "Paul Scholes", 1],[ "@TWC", 1],[ "Bolivarian Republic of Venezuela", 1],[ "#SydneySie", 1],[ "World Food Programme", 1],[ "@BBCNewsMagazine", 1],[ "@VernaMyers", 1],[ "@WorldStarFunny", 1],[ "Basque Country Left", 1],[ "@codyincalgary", 1],[ "@M_McDonough", 1],[ "Billy Reid", 1],[ "Nick Clegg", 1],[ "@maplegoh", 1],[ "#Yorkshireflags", 1],[ "@JosiahDelagarza", 1],[ "Ariel Castro", 1],[ "@DFATD_DEV", 1],[ "@maddy_NTHC", 1],[ "Alien Planet Spotted", 1],[ "@lakedistrictmba", 1],[ "ina East", 1],[ "#Sydneyseige", 1],[ "Public Transport Authority", 1],[ "#ngp", 1],[ "#Adelaide", 1],[ "#UnderwaterSelfie", 1],[ "#China", 1],[ "Angels Game", 1],[ "@SBCoffeehouse", 1],[ "@indykaila", 1],[ "Boston", 1],[ "#myzeitgeist", 1],[ "@KenRoth", 1],[ "#TortureReport", 1],[ "@Cryptogeeks", 1],[ "@JuanTheWorld", 1],[ "Enhanced American", 1],[ "Namibia", 1],[ "@wincewong", 1],[ "@Forbes", 1],[ "@shahamshi", 1],[ "Pak Taliban", 1],[ "@DefenceHQ", 1],[ "Civ5", 1],[ "#GMRS", 1],[ "@NahBabyNah", 1],[ "Lightswitch", 1],[ "@News1130radio", 1],[ "#BoydBence", 1],[ "#BurnabyMountain", 1],[ "@perehuguet", 1],[ "Encyclopaedia Britannica", 1],[ "@Mock", 1],[ "@DavidColeGtown", 1],[ "#Sinjar", 1],[ "@chapus2012", 1],[ "Hallmark", 1],[ "#LahoreShutDown", 1],[ "@ArcBladeWaltz", 1],[ "Beckham", 1],[ "Kronk", 1],[ "@magicalmorganx", 1],[ "Mitt Romney", 1],[ "Squadie", 1],[ "Alfred Hitchcock", 1],[ "Darlington", 1],[ "Carla @CarlaPillco", 1],[ "@businessinsider", 1],[ "#UCWRadio", 1],[ "Thamesmead", 1],[ "Ross Kemp", 1],[ "TICKTOCK", 1],[ "#poordraymen", 1],[ "@cberkman", 1],[ "@OpenSociety", 1] ], "groups": ["@BBCBreaking","Sydney","#sydneysiege","military police","#sydneyseige","National Security Committee","#SydneySiege","United States","Russia","#illridewithyou","#Sydney","#PeshawarAttack","Pakistan","#Peshawar","Commonwealth of Australia","@RT_com","@cnnbrk","Peshawar","Santa","Ferguson","@nabihahk","#mepolitics","#Randirobics","Tony Abbott","#Parents","@PaulNBlake","@nytimes","@DrLaryngeus","@BBCWorld","Apple","Isis","@BreakingNews","Martin Place","#Vegan","@CNN","#Pinterest","@ZahraBilloo","#Recipes","@pracca","#healthylifestyle","#Moms","Lindt","@chryslap","@KQEDedspace","Facebook","@nswpolice","@BBCNewsUS","@CNET","BBC","Hull","Sony","#Ferguson","@mariamsobh","@aashi__","@TheEconomist","Canada","@ThierryHenry","CIA","@DailyMirror","#boydbence","United Kingdom","@9NewsSyd","Instagram","London","@guardian","@cnewslive","@DailyMailAU","Putin","@cnni","New York","@Everton","@RMadridNation","@Randirobics","#lindtcafe","@WSJ","@Janelle","Kendall","Twitter","General Motors","Thierry Henry","Jo","Associated Press","@nspector4","@AP","@nsb2063","@PepperTheDog","Dios","@VancityBuzz","#Obesity","@m_wotherspoon","Wright","@Eagle_Child","@WorldRugby7s","Ebola","@ONENewsNZ","#9News","Obama","@AssignGuy","@Michaud2014","#Pakistan","ur","@TEDTalks","@UberFacts","@norwellfiredept","@FoxNews","@BreakngNewsPhtg","@Revenger210","@mattdpearce","@smh","@ElizabethMay","@TheDrunkStory","@Mahezabeen","@eirewalsh","@wheelbasecycles","@FootballFunnys","@MoreConsole","Singapore","@ABC","@FelixNater","#EFC","@pioneergirl08","#MartinPlace","@CityNews","@HAKRK","#BREAKING","@psychxdelic","#SCOTUS","Craig","@luisvicenteleon","#Kids","#AppleLive","@JamesBlunt","@BabyAnimalPics","James Blunt","@TheMeninism","Kenya","Ikea","World Cup","@NCIS_L_A_Fans","#Russia","@yonkersoem40","@History_Pics","Paul","FIFA","@9NewsAUS","@shahidkapoor","@fiskcg","#IllRideWithYou","Japan","Oliver","Mary","YouTube","@fizzer18","@DestinyNews_net","@itsadisaster","@uli_speck","@QishRashid","@Brittjabee","Tori Johnson","@CBCNews","@NetControl","@baltictraining","Donald","@NewTechCoppell","Europa","@WowEarthPics","@crisvalverdej","@trmyhre","South Africa","@RelatableQuote","@Bewickwren","@Independent","#Dubai7s","@SkyNewsBreak","#MyZeitgeist","@BuzzFeedNews","Michaud","Katrina Dawson","@MetroUK","#Fox25","@TechCrunch","@marelyndaniel","Max","#awesome","@BBCNewsAus","@BBCtrending","#BlackLivesMatter","@CNNMoney","America","#PeshawarSchoolAttack","Vivek Murthy","@em_ufsee","Pa.","@slvrfnx","#VCB12Days","@TAEVisionCEO","@lumiauk","@EconBizFin","@macinjosh","Crimean","@KCBGroup","#Cortana","#MichaelBrown","Sinclair","GHG","Starbucks Corporation","#Norwell","Morocco","@shebe86","@PantherZone","@MotherJones","@Reuters","#GreenSmoothies","Wallace","@ExportDevCanada","Black Mirror","@AlienTuna","@CityofChelseaPD","Mike","#ruble","New York Police Department","#OutFront","#COYB","@Sydell","@N_Fostell","@carolinemarcus","@PaulRieckhoff","@zoe231177","Cutler","@DustinGFitch","@CoalsonR","Norway","@LassoGuillermo","Atlanta","Adam","Alhamdulillah","Iraq","@tanjooilong","SSW","Leo","Oz","Everton","Justin Bieber","@Daily_Express","@slave2thefav","@Playdoughpoem","@cmanduley","@FootyHumour","Aristotle","Watson","East Millinocket","@TandonRaveena","Sydney CBD","@TIME","@engadget","KL","Orange","@russ008","@mindykaling","@TonyAbbottMHR","@CNNPolitics","@SincerelyTumblr","#ND","@UKenyatta","Cristiano Ronaldo","@EW","@manny_ottawa","@bonifacemwangi","@SPreyzner","Isaac","Starbucks","@cristilmethod","@TheCryptarch","@AnnaDegToGo","Selma","@Ants_SNEweather","@BPreyzner","#RealMadrid","@HistoryInPics","@2014_Neha","@IAVA","Ukraine","@transformers","@StevePhillips7","Ontario","@BuzzFeedOz","Denver","#GreeleyGrizwalds","@SoVeryBritish","New Zealand","#LastWords","@BBCSteveR","@DinaGusovsky","#Pes","#ClayHunt","Cheney","Chicago","Syria","@globeandmail","Giroud","@ReadInimicus","Ava","@CNBCFastMoney","@Bar_staff_probs","@PadreIsrael","Disney","Kyle","#healthyeating","#MartinPl","@TheRock","Truman","@KarinAlexander","#MTVStars","@pactcoffee","Bankia","@exp_juridico","@HamidMirGEO","Sydney Lindt","@FCBarcelona","Apple Watch","@christmas_clock","Mars","Allah","Atlético Tetuán","Jesus","@yogscast","Hague","Brand Ambassadors","@TuksFMNews","@__jolo","@MMP_Montana","@derprevere","Alaska","23 Standish Ave.","Top Cop","@neytauppa","@notcreative388","#Homeland","Philadelphia","Pearson","Walt Disney","@andersostlund","Christine","#Transformers","@ChrisKlemens","Amazon","@DattosDestiny","Press Trust of India","@JoeWMuchiri","ICYMI","@GabbyKaufman","Xbox One","Club World Cup","#SPOTY","Gaza","#mufc","@nonvitaltooth","@nytimesworld","#MakeItHappen","@9GAGTweets","#oil","@ShireenMazari1","@slang4201","@julieplec","@CNNSitRoom","@financialpost","#Australia","China","@ESPINOSAMCCANN","#HandsUpDontShoot","Joe","Christian","@NWDogRescue","@ArtturiArtturi","De Gea","@smebulok","@FriedmansJwlry","India","Franco","France","Diana","@lepage2014","Patrick","Ralph","Storm","Dawson","#Facebook","@GeoffNews","Barnes","#SydneyHostageCrisis","@BillNemitz","#Health","@KyleEvanReed","KFC","@DanaeBoyd","Johnny Abraham","Ferrari","@SimpsonsQOTD","#TeamPW","#martinplace","@azmemunyit","Rehman","@MrStevenGeorge","@MassStatePolice","@fromshadows","Malaysian Airlines","@johnkeypm","@DeeSet","@SETIInstitute","#AussieUnited","Scotland Yard","@MurtazaGeoNews","Leslie","Egypt","@ScotStreetStyle","@ManUtd","Chris","@SoTotallyToby","@lonelyplanet","South Korea","Lewis Hamilton","@arjastork","World Health Organization","Francis","@AneeRsyDney","Michael","@colinjevons","@NBCNews","Harper","@OutFrontCNN","@danny_macaskill","#COP20","@NYTNational","#tvd","@Newsweek","@HSBC_UK_Help","#bcpoli","Kevin","@lolasanya","Madrid","@MissMalini","Schiller","Britton","Ohio","@Rixpoet","#oops","@PumaBare","#PeterPanLive","#Education","@JonChevreau","@niwentweets","@CBSNews","#Science","@Laura_Figueroa","@Lisa_Wilkinson","@Sc0fy_","#FatherTed","@BroderickGreer","#Blood","Molana Fazal-u","@shaunwalker7","Pasir Ris","#Equines","@achufford","@FarahKhanAli","@BBCSPOTY","#brunch","@ThislsAmazing","@BungieInformer","@dpgushee","@richeisen","#YNWA","@TimOBrien","@mrewanmurray","@BarrilVenezuela","#Nutrition","Ahhh Sterling","@BradPittsPage","@GilletteStadium","@GuardianTT","#NeverFeltMoreLikeSingingtheBlues","Gary Neville","Brock Bottoms","@enzadesu","#firemission","#the24cookiesofChristmas","Legend Group","#womenarewatching","Santander","@challot_","Adrien Rabiot","@IBMoghadam","@3pm","@Arsenal","Investigation Team","Burnley","@FrankRGardner","Goodnight","@JRhodesPianist","@swogden10","@TPM","@abcnewsSydney","MTB","@MatthewPrescott","#Racism","@stocktraderwill","#AdoptDog","Harina","Asaad","Spain","@janengoiri","@RFU_RDO","International Airlines Group","#runs","Emilio Estevez","@andymientus","@htTweets","@kagtireema","Vladimir Putin","RNGesus","@matamoros_kathy","#FMRevolution","@JesseRoberts0n","@KBCoburn","#Nat","Romanian Revolution","@GearHeadz28","@FloydShivambu","@diaridtarragona","@falloutboy","@MobileBaySports","President @UKenyatta","Michael Grant","Dressed As Santa","@RBarkley20","@YourHistoryPics","Russell Brand","Rainmaker Files For Bankruptcy","@UmarCheema1","Capitol","Odell","GEO","#London's","@Bibliaenlinea","#CRomnibus","@blackrock","#EOD","@RTUKnews","Sana Mirza","Command Center","Business School","París","@Staleyphoto","Japan AND","@thomaspluck","@ciarale01","@Cristiano","Boston Police","@DannSahak","Acción Comunista","Andrew Cuomo","Sky Sports","#summertime","@deepikapadukone","Ferguson & Ebola","Ms Merkel Putin","@nytpolitics","#hurricane","Birthday Indiana","@ESPNStatsInfo","@ZachsMind","@1LeylaRodriguez","UncleMurda","Fav","@GrayConnolly","David Allen Ward","@A_D1su","@AFP","Zach Roerig","@Sportive23_","#foggytowin","@runnersworld","Maya Angelou","#climatechange","@SarahMillican75","@WMTWTV","#derisking","@ToxicFox","@your_screen_name","Caja Castilla-La Mancha","Waitin Fr","@Siva_Kartikeyan","Russian Central Bank","@almudenavigil","#god","Cove","Brian Lara","#KXL","@jerryagar1010","Harry","@Teespring","@OhMyHani","PTI","MNF","#REF","@VengeanceRacing","#wcvb","@MrActuary","Filipinas","Red Square","#environmentallyfriendly","@CiboMattoCiboMa","@ScienceBasedMed","MMO","@wjrothman","@DigitalLookNews","@Fareeloydias","@Truman_Black","@stephca","Mascot Challenge","@GidgetWA","With Admitted Former Crack Dealer Jay-Z","@RJSzczerba","@WBBMNewsradio","Lahoris","@therealcliffyb","@markondefense","@okothkenneth","@expansioncom","@GOP","#Christmasjumperday","@BBCTHREE","Dolly","MLK","@NYCCouncil","Betsy Smith","#hatesuffocatesprogress","@allkpop","Broadway & MacDonald St","@adamrichard","Telstra","@Dubai7s","@iScotNews","@baddyaddyy","@APHClarkson","@tariqmughal68","@ATLblog","Golden Globes","Angels Jannatul Firdos","@newtgingrich","#SeriouslyStrange","@kristenhare","Jamhuri Day","#Meograph","U2","@VIVErevista","#CristianoRonaldo","@morningmoneyben","@NBCSports","#MyZ","#EbolaResponse","23 Standish Street","#OffTheRecord","@nonstopwardle","TD","@jenanmoussa","@takouris","#Victory365","Saint Louis","@nationalpost","Megabus","Lingaa","@officialroycey","@KoinangeJeff","@bukorilaalamak","Adam Levines","#BOCapsule","Man Haron Monis","@TRobinsonNewEra","SC","Einsteins","@funnyortruth","Qu","RV","Torres","@nmcrooks","@DaveHaygarth","@sadiaacee","Google, Inc.","@brittanyr","@orestimusic","@MYSADCAT","Monty Python","@H0XH4","@chrisklemens","@ExUnitateVires","#LoneWolf","It Go","@DavidC516","@Gem_Davies","@londenbell","Statmnt Taliban","Iran","New Year","@BBCNewshour","@NewTechAoife","@jamestaylor20","Jesús","@Nkomati_","Nassau County Legislature","#TVDS6","@Bryan_Oviedo","@ULTA_Beauty","Petrobras","@Cher","#UQ","@RichardDawkins","Rory McIlroy","Man City","@TheSaucyFucker","#infosys","#Iglesia","Will Receive","PE","PD","#Kolchenko","@TonyPitchford","@aedurkin","Caroline @RiskAlert","Flippin","@DanceEatRepeat","#JamhuriDay","Afghanistan","@theIRC","Matt Dillon","OU","@WHO","Russ Feingold","@ErikaWCVB","BT Group","Discuss Police Policy","@CityNewsAmanda","Birth Vs. Kick","#YouthEmpowerment","@droblopuntoes","@cocaineprada","#PeshawarAttacks","@MahmoudRamsey","BUHARI","#Vancouver","@Canada_Business","Éric Cantona","PCLN","@TheRaDR","@President","@paulla","@rachaeljacobs","NY","@LeeannWright4","#News","Royal Albert Hall","#PrayForSydney","#Tech","@WhiteVsBlackTwt","Mo","Zuma","@poptartqueeen","@MaryamNSharif","@AwAKAning04","@KA_Gould","#MyRecruitBoard","@Official_NFFC","Ecuador","Newcastle United","Greta Garbo","New York St","@JLo","Caller","Eric Garner","@BleacherReport","#WIsen","Book Giveaway","@WFP","@SEIU","#KingHenry","ForeverStars","Pan Africanist Congress of Azania","Shoutout","@SkyNews","Mobocracy","Fbody Nation Kids","@NOD008","@paulapoundstone","@NPRNews","@newscomauHQ","Dietmar Hamann","Stone Cold Steve Austin","#iphone","Prince George","@codyk","@PiscesAreUs","WCSH","#6thcircuit","BBVA","@CP24","Citizens' Action Party","@forex_futures","Hotpot Supper Tickets","#HowToGetAwayWithMurder","LG","@voxdotcom","@OrchardGateway","@noaaocean","@jonathansamuels","@ricardo_hausman","@MercianRockyRex","Darth Vader","#money","@girlposts","@TanujVirwani","Josh","@stephenfry","21 Jump Street","@HackneyAbbott","@AnsarAAbbasi","#KyDerby140","NECBirmingham","@mediocredog","@dopesoph","@Scripture_Truth","#wouldyouaskaman","@SupraStrong_13","ToriJohnson","CNN","Haqqani","@LFCfamily5","#enzo","@akhilak","Aviva","@Capitancarloc","@sciencemuseum","APHClarkson","#evolvingcity","JV","@LtGovDuffyNY","@ntvkenya","@sosmaydan","Monaco","HAHAHA","@jaltucher","@BillMoyersHQ","@screenrant","OOOOOOOMG","CUTEEE","Fuji","@AdamSerwer","La Libertad","Nadia","@theedgemarkets","#icantbreathe","CMH","@dawn_com","Pacific","Pryor","@BFMradio","@Newsday","@DMiliband","#NH","Bloomberg","EEOC","@FT","Brendan","@Taranaki_NZ","England","@bostonpolice","#travel","Standish Ave.","Geo @MuaazAhsanGeo","@michaud2014","Gx","Miami","Aviva plc","Land","@dmardiste","Paul Revere","@larramalik","#suzesays","University of Valladolid","@ShiaPrincesss","Passenger Transport Authority","Podolski","#Fitness","VOIP","Pak Army","Malick","@qurratuzainudin","Angels","Wales","@Troll__Football","#SouthAfrica","@USARugby","#HealthIsPrimary","#tvds6","International Baccalaureate","#MeriBandook","@ABC7NY","St. Louis","@Waisale_Serevi","#Abbott","Matthew Bourne","@ystriya","@BBCSport","G20","#tcot","#gooner","#Runrunes","Surgeon General","@CoppellHigh","@BBCSporf","#Toronto","@JamesStewa","@flintbedrock","@LaylaaSays","@PRI","Gwen Moore","@Bu","@perlimaya","@nadeemmalik","@tufkaa","FA","Hmph","Overseas Sports Personality","Thundersnow","@jmcotelo","Missouri","#Hailstate","London Gatwick Airport","@LUADJeff","EW","@DTRubenIsrael","@msnbc","@BOCapsule","@Saj_PakPassion","@vikramchandra","#mcwccx","#addicted","PBA","@AsimBajwaISPR","@LFCTS","Banco Central de España","YTD","@AyseErinc","Mukherjee","@SocialRMadrid","American Psycho","Heathrow","@LauraBenanti","Cazorla","@HDNER","#NALS2014","Govt","@randybillings","Bill Powell","#IS","@bbcweather","@megynkelly","@MichaelaK33","@whereisnate","Steven #Naismith","@rockportbasset","#Angels","Earthquake","@Schuldensuehner","@AuburnJokes","@voguemagazine","Ian Supra","@wajih_sani","#CERT","FMT","@billshortenmp","Tom Coburn","@fijirugby","@HniaziISF","@Scott_Gilmore","@POLITICO","@CRonaldoFans15","@tweethutchy","#ManderaQuarryAttack","@TamaraMcCleary","@FatherTedSpeak","@BostonNewsMan","#Lindt","@pourmecoffee","Republican Bill Cassidy","#ISupportSanaMirza","Staveley","Jesé","CB","#NationalTrophy","Happy Home Company","#notimpressed","@WSJPolitics","@dailytelegraph","Al","@SCNosalMD","Loaded Baguette","@BuzzFeedIndia","At Sydney","Sydney Opera House","#MillionsMarchNYC","@ansarAAbbasi","BB","#Aliens","#thanksskipper","M'sian","@karrar_meer","@portalkritis","@SuzeOrmanShow","#EnviroIntel","@chrisshipitv","@TheFoxandCrown","@MaineDems","@atlblog","#magicalTuesday","@begumtothestars","@tdy_T","Reuters","@KCChiefs","@PurelyFootball","#Adopt","Thomas Howell","#food","PKR group","@EconEconomics","#Recruitment","@carlfogarty","#AllOfTheLights","#MerciThierry","#London","Racing de Avellaneda","Birmingham Crown Court","@thehill","Taliba","Far Cry","@DavidSchawel","Leinster Ploughing","#Ghent","Android","@EARMILK","#digitaldiplomacy","Germany","Hmm","@Metrorailinfo","Netflix, Inc.","Dania","Yorkshire","@ConfuciusPosts","@realmadriden","Big Bash","US Airways","@earthepix","#finishthejob","Champions League","#SYDNEYSIEGE","#UofA","Proud of Nassau Legis Dem Ldr","Dejan Lovren","Maine","Tilda Swinton","@CSPhotoscom","Sydney Cafe","@MtbSprocket","#snl","@AnaGtz79","#RussiaMeltdown","@Ashton5SOS","@ExcellentAnimal","#AsiaPacific","#pakistan","Dini","#Sentsov","#Live","@FJ0hana","@JWTelegraph","Banco Popular","#AMAs","@pretoriacoza","Mva Northborough","Talley","Empire State Building","@KTNKenya","@ObesityBlog","@HuffPostUKPics","@tom_harlock","Oohhhh","@Prem_S","Luis Enrique","Messi","@boohoo","@MailOnline","Sherlock","@FutbooIFichajes","@SputnikInt","@TheStrippin","Jakell Mitchell","#thesimpsons","@iamthekartel","Good","@BoniMtetezi","@BBCNewsAsia","#June27th","Geo @MurtazaGeoNews","LRT","#bikeracing","#Mirallas","#theKenyawewant","Wenger","@BrendonWu_","@BBCOS","@SunVoip","@Grand_Theatre","@ashsperls","#AN","Getty","#AL","#cupcake","@Brianmbunde","Cristiano","@EuromaidanPress","@ABCNewsLive","@Benogola","@bengollings10","The Sun","Eco","#sosingaporean","@azhairul","@broadwaycom","Tehrik-e-Taliban","#monash","#WorldAIDSDay","Madeleine McCann","La República","Nuh","First Family","@YYZemily","@thescript","#smartmoney","@Angieyy_","The New York Times Company","Lewis Craven","Man Utd","National Guard","Knn","Kot Radha Kishan","#fieldmarketing","@Oogwae","@MirrorRowZed","Venus","Fatou Bensouda","@FortuneMagazine","@SAMAATV","@ShiversDorhout","Lee Rigby","#pets","@Kevan_Abrahams","Optimus Prime & Bumblebee","#coffeehousecool","@tbhjuststop","@JessicaValenti","@MediaGhuru","@Baird","Sumatran","Chelsea Man Wanted","@banditocado","@QuadFins4Fun","@pdacosta","#econarchive","CycloCross Trophy Bradford","#ChristmasInWashington","@tmerilaht","@rioferdy5","In & Out Burger","@Winyy__","@sharmeenochinoy","@AGMuigai","@RaqiyahMays","Pakistan Taliban","#AFCvNUFC","@simonrademan","CNNgo","@bigboyja","#WhereTheMagicHappens","Darren Wilson","As Long As You","Wood & Steel","@mahezabeen","Woooh","#PolScotRecruit","@juliamacfarlane","Vine of Sen.","Palestine Bombings","Lord Saladin","Uncharacteristic","Mehmet Ozlap","#Space","#CrushT","John Ivison","@harristweedheb","North St. Paul","UberPop","@svarun_01","Waze","@VideosOfScience","@breakingbytes","@robjillo","#BelgiumSiege","@rebmatius","@UP_TownCenter","Aww","@WNYC","Cup Third Round trip","Metrolinx","@dfarmer14","#YearInSearch","@BBCLancashire","@JMLudes","@uscensusbureau","@D_DeGea","#Sydneysiege","@PBS","New South Wales","@Nanmanea","@eNCAnews","Petsmart","@JamilSmith","@ibieberlinear","Federal Reserve","#tosua","@Reu","@talyellin","@ChrChristensen","@Majid_Agha","Silent Nemo","@JackJackJohnson","@realDonaldTrump","@anonoMAN42","@TheCRonaldoFan","Bangkok","Kaddish","@latimes","@Jay_78_","@ProfJessieSmith","#PakSchoolSiege","@MyUNiDAYS","@YahoodiSaazish","@SpursOfficial","#DisneyOnBroadway","#Chiefs","Bublé","@HawksheadBrewer","@tlrd","Lahore","@OracKnows","@HuffPostUK","#G20Brisbane","Jagerbomb","Ask of You","@capricecrane","@WXII","@jehuegordon","Tesco","Hollywood","@GRlMDAREAPER","@philwcvb","@VisitNC","Matt Davis","Andalusian Party","Scarborough","Comcast","Rob Lowe","#productivity","@NewAmerica","@takiafaridah","#Dubai","@maryslandmovie","Songs of Innocence","@NYS_Ke","IBM","Cassian","@lynnOnCrime","@meganamram","@TomCoburn","Nicolae Ceau","@RoomeeTimes","@UpshotNYT","Ray Lewis","#adoptable","Nome","#alaric","Seventh Avenue","@Contentions","Muslim Community","#thankful","Harina Pan","Arc","Banco Santander","@LaundyCraigMP","@STERLINGMHOLMES","@Mobkay","Jeez","Kiska Volcano","@kdastgirkhan","@EngadgetUK","@NHDavies13","@BoxOfficeMexico","#illridewithTori","#tweet4taiji","Acción Católica","@mencap_charity","@yourfamilydoc","Mississippi St","@WladimirZanoni","#carrotforacock","@AlyssaCRaley","#Montgomery","#KyDerby","George Stinney","#AdoptCat","@AshleySiegs","#medwomen","Servicio de Atención a las Víctimas de delitos violentos","Weekly Nightfall","#Cat","Polo Sweet Bag","Camille Cosby","COPS","@TheSimpsons","#Hull","Virat Kohli","@JennyWCVB","@MMViverito","@Canada","@Ziya_Meral","Barbie","CRISTIANO RONALDO PORTUGAL","Housing Unit","#CHISpaVan","@albinlilas","Parakas","Sneijder","@CarolCNN","LDP","West St. Paul","@StefSimanowitz","@jarelkun","#AmericanHorrorStory","@business","SHVETSOV","@TheRunningBug","Sydney Morning Herald","#DENSI","Military Intelligence, Section 5","@SammyTellem","@elblogsalmon","@ohimsosure","Bay Area","AmerUs Group","Gov't","Ballon","#FieldMarketing","@LiamGillham93","Humboldt County","Kar","@BilldeBlasio","#Cyclocross","M.Serraller","#boydbe","@CallyGingrich","@IEPI_ecuador","@bronwen","Rail Fun Day","Greg","@GoalUK","#Entertainment","#DerechosHumanos","@KenyaPower","Pervsis","Julio Jones","@HolidayInn","#26","Police Se","#MateShip","@DogsTrust","@SkyBet","@howardlindzon","Cairo","@newtechrebekahp","Kiev","#FarmMurders","Greeley","@Fred_Delicious","PIXXX","@HeathrowAirport","@LBoucher77","#15","@DBessClass","Ma Rte","@Channel9","@yanchooow","@CTVVancouver","@VirginTrains","@guardian_sport","Deputy Commissioner Catherine Burn","#FallOutBoyABAP","@NYCEMSwebsite","@kunalkohli","East Pakistan","Pearson Educación España","@FIFAcom","@supcollins","Panther Nation","@DLoesch","@SunnyLeone","@CA2015","Pelham NH","#EastEnders","@ezralevant","#welikemike","BETTA BRENCH","Dodgeball","@SelfieNigga","@BabyAnimalGifs","#Nassau","Tesco Corporation","@Instagram","Anushka Sharma","#Competition","@MIRAMETV","Paris Saint-Germain Football Club","#vietnambelievable","Tmn Tun Dr Ismail","Tom Cruise","@BN247","Harris Tweed","#CongressInOneWord","@JuliaDavisNews","@wbir","Bangladesh","@sehunsqueen","@downriver_b","@INTHENOWRT","#THFC","Male","@GrangerKate","@etribune","United Arab Emirates","#PTI","@ALcomMobile","@ATHE1STP0WER","@ClaireaBellaLtd","Mugshot of Michael Crooker","Gerald Kaufman","@SaifRRahman","@SenFeinstein","@Iamksgofficial","Cali","Residual Value Awards","Google Zeitgeist","Digital Crown","Lions","Narendra Modi","SabahUS Dollar","Ahh","@Talkmaster","#Showtime","@Know","@itvnews","#Finally","Liverpool","Kansas","#Wellness","@liptika_","@AshmanAmirudin","@huntersbayradio","@Kimmyincali","@AsliHaroon","#Sweeps","@PPMEAF","Make Your Own Double Helix Xmas Tree","Channel 4","Upton","@BBCNews","The Museum","@TheAnonMessage","#Mencap","@Vnmol","#workinghours","Rhode Island","#OviedoBaby","@StandardIssueUK","Mark Owen","CM Balochistan","@RussOnPolitics","@NerdyWonka","#HA1LSTATE","@UkraineReddit","@CruzRojaEsp","@K_Simmz","#genius","@KimKardashian","@NewsHour","@HuffingtonPost","@CBSFantasy","#GiftGorgeously","@m_cof","LDMBA","#KentuckyDerby","#bbcqt","Aamilah","@google","Pro Sc","Julie","@fasiranjha","@bobatl","Brazil","#alwayswelcome","@YourAnonNews","@studentawards","Fernando Soto Rojas","@RaissaAlmanda","@James_Baltic","@Cookstar118","@SuccessfulIy","@MaajidNawaz","Roundup","@Coppellisd","#l","#FindingDory","@VisitLancashire","@AdrianaStuijt","Fort Lauderdale","#g","@SoSingaporean","High","@KenyaRedCross","@iamwill","la Caixa","@JODYHiGHROLLER","Liverpool F. C.","Ebola-hit West Africa","#VIRAL","#Kenya","@ArupThoughts","@runzourry","@twirlyswirly","#Scanning","Señor","Chris Brown","#marriage","Samsung Gear","Springarab","@SenateDems","#BCPo","#PatriotsNation","@grenouf","@SteveMarshallNZ","#NOAA","#2","@NickHanauer","@stalemt","Sky News Australia","@PickeringTj","#Scandal","@RealPaulWalker","#Taliban","#Chile2015","@KathyHochul","@jennablan","#ableg","Marca","KingHenry","Google Maps","Gracias Cristi","The hotel","Louisiana Democratic Sen.","@ShoeMeCA","#MH370","@chrisgailus","Justin","@MikeFriday09","@SCC_Barcelona","Alan","#Brazil","@LFC","Steve Young","@NewsOnTheMin","@Prevent_Obesity","#Radio","@ldbene10","@tanehisicoates","Saskatchewan","@awkwardposts","@Business","@gst183","Jani","#PLL","#EBOLA","@JackDromeyMP","GOTV","@TheDailyEdge","King Henry","ENIPLA","#Eyecon","Daily Sabah","@arjunk26","#AUBvsMSST","Panic","@saks","#DoNowFerguson","@TEDxBeaconSt","@NOAA","Cruz Azul","#askfast","@jimpoco","#OneNightStand","#gamergate","@MetPoliceUK","@SHO_Homeland","@SteaknShake","@comcast","@alsmiffy","@usgs","Hillary Clinton","@ComedyOrTruth","#inspiration","Izquierda de Cataluña","@jimmyfallon","@Reverend_Scott","@NelsonBocaranda","#PUSKAS","Stream of the Lindt Cafe","@CNBC","#IAmMyKenya","#BearGrylls","@SkySportsNewsHQ","Frank Sinatra","Massachusetts","#TrayvonMartin","@NewsHourExtra","David Suzuki","@newtechmorgan","Carrà","@NicolasMaduro","Happy Endings","@mehransanam","@CNNOpinion","Florida","@kaytazb","#FMRevoluti","@nickconfessore","@MountVernon","the Guardian","@WkyJoven","@AlexBrown77","@AnneWaiguru","Champions League Last","@_evafox","@TalatHussain12","B'way","@LBC","@TheWilsonCenter","Corel Draw","@RamzZy_","@PTXofficial","#fox25","@BookOProverbs","Roku","@KyivPost","Chile","#SkyBetTransferFund","@ShangriLa_Van","@WSJAsia","@hitRECord","@Battle","@XboxQwik","Gauteng","#EricGarner","Crimea","OHMAIGOD","@HaseenaAtomBum","@AnupKaphle","#Northboro","Game of Thrones","McPherson Square & L'Enfant Plaza","Oprah","#PoliceState","@ImBossyBoots","#TopDocNow","#Hersheys","Aqib Talib","Surveys of Mars","@imVkohli","@TheScotsman","Federal Reserve System","#climateaction","lesbian gay bisexual/pansexual and transgender people","@Julius_S_Malema","Simon Harris","Best Music","#CHRISTMAS DAY","@paulhicks63","#Sevens","@KayBurley","@RiteExpressions","Randirobics Galactic Gazette","@Gaetano_lo_hace","@NYCGreenfield","#Malaysia","@BBCr4today","Uber","@yv","@newsday","@MayaLand3","#CHRISTMAS","En12","Ferguson Missouri","@TheWorldImages","@troyesivan","#OrangeIsTheNewBlack","@ReutersLatam","@Ghetto_F0X","7News","Sheena","@TheLadBible","@CoveGuardians","@Bellows4Senate","@Nashgrier","@HouseofCards","@atiku","@MKB1A","#Bradford","Amal Clooney","@nicolasmsarries","@English_AS","@Joey_Del","#Crimea","@kids_exercise","Walford","@sailorkilljoy_","@l0lbac0n","@GAVI","@PzFeed","Lion","Most Popular Searches On Google In","@Tempibones","John Crawford","@GregSmithMD","@kashf7sab","@ScanBC","@BanuBCicek","@Mannam_92","París Saint Germain","one fucked up place","Reuters Opinion Strobe Talbott","@PLASTICPLATES","@LogitechG","@grg","#RWWinterWeek","#RugbySevens","Surkov Lt","#burnout","@moody","#Foot","@kravsazzle","@MockMavPam","@RosalieBardo","#matt","#BenStiller","#GTHOM","@KingdomWildlife","#SouthSudan","Rio de Janeiro","Howard Schultz","Pslam","Cosby","Department of Corrections","@gedikaslihan","Afric","African Union","El Nido","#AAFPNCCL","@ProBirdRights","James Altucher","@news_va_es","@brithume","@nikicheong","Orlando","#ReyesparaTodos","Rachel","Queens Park Rangers","Hero","Lima","President Uhuru Kenyatta","Holiday","@IMAXSOFL","El Salvador","#Blackpool","@Tim_Ste","@RD_Economist","@FtLauderdaleSun","Nigeria","@Marcasur","#ParksAndRec","#news","@sonamakapoor","@intelwire","Benjamin Franklin","#Indiawithpakistan","@EliotCutler","@nyonair","Beenie Man","Camille","@southernsnowgal","@foofighters","@jesserbnwtz","@Skrillex","@nytimesbooks","Bill","@rarestcat","@DFWscanner","@southsalem","@GaryLineker","@fox25news","@bipsluvurself","@backstreetboys","@LadySandersfarm","@GetTwistedRecs","Belgium","everton @RBarkley20","@toughlovemusic","#TheLeftovers","#SpreadLove","@oaarchitects","Valencia","@AmiriKing","#corvette","HBO","#Mandera","@washingtonpost","@AllisterHeath","@KrisPoB","@TalatHussain","#chinesetakeaway","@ReutersBiz","@SundayBrunchC4","@OilsandsAction","Annual Shop","@mathi8888","#Drones","Google","ULTA","#MAtraffic","@anirudhofficial","Weather Bomb","Olympia","#TierraDeMaría","Steve Bell","@mubasherlucman","@bbcworldservice","@KazimAlam","London Bridge","@Jess_Baltic","@SkyNewsAu","@njiiru","@craigadams49","#z06","@Express_Pics","@MASCA_National","#ISIS","nueva moto","California","@Ayeshatakia","#books","@NatGeo","Tottenham Hotspur","@freedomtomarry","#Gillette","@judmoo","#PassItOn","@hitRECordJoe","@LinusKaikai","@JulesBistro","@rezaaslan","Courtesy Marco Hartz","@BJPLucknowBJP","@Prophecy_YEC","#SaksHoliday","@BBCYaldaHakim","#recruitment","Kenya Navy","Frisco Melt","Putins","@DeleMomodu","GENE KELLY","@ernestorileyita","@siberianluck","Dallas","Metro-Goldwyn-Mayer Incorporated","@TheEllenShow","@analitica","Travis Kelce","@ARothNYT","@MrMichaelSpicer","STFU","Vietnam","America Herald","Moulin","@maddow","#SoulOnFire","Wilson Airport","No Bake Chocolate Cookies","Ridley Scott","@mckenzierose","Red Crescent Islamabad","@TDR_Network","@FairQuestions","@INTLSpectator","@TroyAikman","Jan","Korean War","#CapitalPunishmentForTTP","#MPAC14","@BlogApprentice","Awuor","Kentmere","@cathy_macdonald","@LaOpcionV","#underwaterhousing","Enfield","#Preparedness","Gervinho","#KConmymind","@va_va_vati","Punjab","#siegeselfie","@ThaPrinceTaylor","@svcred","Eurobank del Mediterráneo","@KAUSHALVYAS23","#raise","@JimmyVielkind","#Newsday","@JohnMbadi","@depericias","@NewEarthquake","@astroehlein","@PhxKen","#YogscastJingleJam","@ChiefsReporter","@erikagparas","@iamthatgirl","Blackboard, Inc.","#brandmanagement","#Destiny's","#sy","@Naira_TVD","#powermatters","#LittleGlobalCitizen","Australia PM","@meredithfrost","#GodBless","Based Telescope","@UCWNews","@CanariasZEC","Tenerife","@BenjaminNorton","With Fries","@LocatScotland","@JONWEXFORD","Malaysians","Sunset Overdrive","@MethuenPolice","@seb9011","@nz7s","Bugis Street","@jamtfe","@MyRecruitBoard","@Chelsea_Goulden","Chris de Burgh","Optus","#heartbroken","@GradElitism","#WCVB","@policescotland","#notankers","@kunalnayyar","@rtked","Pit","#EconomicDecline","#EggBowl2014","#putoutyourbats","@tkelce","@PoderJudicialEs","@splcenter","Eskom","#project543","Pic","WWE","@Markthewise","@shafidpk","@Crossfire","@AlertZaAfrica","@BBCNewsnight","@OwenBennettJone","#macaroons","Erdogan","@CivGame","@ScienceFuture1","#humans","Port Elizabeth","#suicide","Rude","@realmadrid","DID DE GEA","@SanaMerza","RM10k","@AnupamPkher","Pattie","@CNNFC","Ken Okoth","@Jordanems","#Balochistan","@staronline","Malala Yousafzai","Alabama","#volcano","Freshies","Barakah","@03gibbss","#Pisces","#icanshowyoutheworld","#XboxOne","@JavedAzizKhan","Balotelli","@ReutersUS","#wontbelongnow","Wes Welker","Yung Chunky","@BloombergNews","Spotify","@TelegraphPics","@HSBC_Rugby","Imran Khan","NBN","@ChrisReason7","@sierraboggess","@sheridanvoysey","@Stoked4Saturday","Young Pak Arm","#trending","#yogjam","@NATSPressOffice","Shenna","Edge Markets","@PastorTullian","#samoa","@SmahmoodS","#Gamers","@AbabuNamwamba","Novorossia","@ecuavisa","Cameron Mackintosh","@HennaK5","#GraciasMas","@sweatitoutmus","Lionsgate","@marcmarquez93","Hit Medley","Jamaica","@BenThomasPreps","@MarcSchwieger","@fpinvesting","@AsiaPacNews","@EntMagazine","@LOLGOP","@Declaracion","Mike Brown","@ec","#lp","Dogs Only","#HumanityRestored","@GovChristie","Pablo Ruz","Magreb","@russian_market","@Rockettes","#Northeas","#NCISLA","Held In Downtown Sydney Cafe","Marruecos","@FinnWittrock","@KPilkingtonQ","@iambohemia","Navidad","@deepali_shree","Our War","@_cassian","Dunya News","#PakistanSiege","Connection With Double Shooting","Yus","Ex-Dewey Partner","@mradamscott","RM10","Anderlecht","Liga de Fútbol Profesional","Pretyy","@PleasureEllis","@Abogacia_es","@OilandGasInvest","Shah Alam","Van Ruymbeke","Loving You","#xfactor","Lear Corporation","Hatttte","Wetten Dass","Container Khan","Rubio","@FrTedQOTD","@judz5","@nbc6","Ameen","@markchampkins","@Brilliant_Ads","Kitchen Nightmares","Prime Minister Tony Abbott","@urjc","Granddaddy","@BarackObama","Child Inn","@LOLsuren","@greta","@Glinner","@DanielGruchy","@scsj","@CBSShowbiz","@jimsciutto","Young Men's Christian Association","Pfft","Mary Landrieu","Ay Chiamo","Leo Messi","@INdnrnews","Cheryl","Allah SWT","@BTUpdates","@PaulMerrillWMTW","@krissybri","@saxenavishakha","@BradFrenette","#LFC","@ReutersLive","@MCHammer","#mateship","Shaun Lander","Paul Scholes","@TWC","Bolivarian Republic of Venezuela","#SydneySie","World Food Programme","@BBCNewsMagazine","@VernaMyers","@WorldStarFunny","Basque Country Left","@codyincalgary","@M_McDonough","Billy Reid","Nick Clegg","@maplegoh","#Yorkshireflags","@JosiahDelagarza","Ariel Castro","@DFATD_DEV","@maddy_NTHC","Alien Planet Spotted","@lakedistrictmba","ina East","#Sydneyseige","Public Transport Authority","#ngp","#Adelaide","#UnderwaterSelfie","#China","Angels Game","@SBCoffeehouse","@indykaila","Boston","#myzeitgeist","@KenRoth","#TortureReport","@Cryptogeeks","@JuanTheWorld","Enhanced American","Namibia","@wincewong","@Forbes","@shahamshi","Pak Taliban","@DefenceHQ","Civ5","#GMRS","@NahBabyNah","Lightswitch","@News1130radio","#BoydBence","#BurnabyMountain","@perehuguet","Encyclopaedia Britannica","@Mock","@DavidColeGtown","#Sinjar","@chapus2012","Hallmark","#LahoreShutDown","@ArcBladeWaltz","Beckham","Kronk","@magicalmorganx","Mitt Romney","Squadie","Alfred Hitchcock","Darlington","Carla @CarlaPillco","@businessinsider","#UCWRadio","Thamesmead","Ross Kemp","TICKTOCK","#poordraymen","@cberkman","@OpenSociety" ] }}
